<mission_data version="1.7" background_id_arme="8bf1c774-cd5c-41e1-b463-2a543cc7fbd4" playerShipNames_arme="TSN Sabre\TSN Valiant\TSN Lancer\TSN Stalker\TSN Viper\TSN Horizon\TSN Necessity\TSN Hunter">
  <start name="Start" id_arme="8bf1c774-cd5c-41e1-b463-2a543cc7fbd4">
    <set_variable name="Coordinate X" value="597.0" integer="yes" />
    <set_variable name="Coordinate Y" value="243.0" integer="yes" />
    <set_variable name="Alignment" value="Hegemony" integer="yes" />
  </start>
  <folder_arme name="Sierra System" id_arme="e9246d5c-950d-4fec-a3ee-d076de7edef0" />
  <folder_arme name="Sierra Settings" id_arme="f3c59cb5-0313-4447-af42-86dc6c1feffd" parent_id_arme="e9246d5c-950d-4fec-a3ee-d076de7edef0" />
  <folder_arme name="Sierra Menu" id_arme="8933d759-51fd-4d3b-986a-95780cc5141b" parent_id_arme="f3c59cb5-0313-4447-af42-86dc6c1feffd" />
  <event name="Sierra Active" id_arme="337134ea-f9d6-433b-9cce-8a40014d2f9b" parent_id_arme="8933d759-51fd-4d3b-986a-95780cc5141b">
    <if_variable name="Activation Menu" comparator="EQUALS" value="1.0" />
    <set_gm_button text="Lower Arc/Sierra System" />
    <set_variable name="Sierra Gate" value="1.0" integer="yes" />
  </event>
  <event name="Clear Menu Item" id_arme="a949a464-0553-4fa8-8644-0faeb49a723d" parent_id_arme="8933d759-51fd-4d3b-986a-95780cc5141b">
    <if_variable name="Activation Menu" comparator="EQUALS" value="0.0" />
    <clear_gm_button text="Lower Arc/Sierra System" />
  </event>
  <event name="Sierra System" id_arme="574f28a8-7e17-4b5a-90c7-6c325f681710" parent_id_arme="8933d759-51fd-4d3b-986a-95780cc5141b">
    <if_gm_button text="Lower Arc/Sierra System" />
    <set_variable name="Sandbox Activation" value="3.0" integer="yes" />
    <set_variable name="Sector" value="102.0" integer="yes" />
    <set_variable name="Sierra System" value="1.0" integer="yes" />
    <set_variable name="GM Mode" value="3.0" integer="yes" />
  </event>
  <event name="Default System Side" id_arme="6c13911f-0a70-4fe6-9625-86714d51a993" parent_id_arme="f3c59cb5-0313-4447-af42-86dc6c1feffd">
    <if_variable name="System Settings" comparator="EQUALS" value="1.0" />
    <if_variable name="Sierra System" comparator="EQUALS" value="System" />
    <if_variable name="systemSideOverride" comparator="LESS" value="1.0" />
    <set_variable name="systemSide" value="2.0" integer="yes" />
    <set_variable name="System Settings" value="2.0" integer="yes" />
  </event>
  <event name="System Side Override" id_arme="cd61a7d0-01a8-403b-8b23-8b0c34bdac65" parent_id_arme="f3c59cb5-0313-4447-af42-86dc6c1feffd">
    <if_variable name="System Settings" comparator="EQUALS" value="1.0" />
    <if_variable name="Sierra System" comparator="EQUALS" value="System" />
    <if_variable name="systemSideOverride" comparator="GREATER_EQUAL" value="1.0" />
    <set_variable name="systemSide" value="systemSideOverride" integer="yes" />
    <set_variable name="System Settings" value="2.0" integer="yes" />
  </event>
  <event name="Sector Side Override" id_arme="3f602d27-595b-43f1-8fdb-b80385a8ec79" parent_id_arme="f3c59cb5-0313-4447-af42-86dc6c1feffd">
    <if_variable name="System Settings" comparator="EQUALS" value="2.0" />
    <if_variable name="Sierra System" comparator="EQUALS" value="System" />
    <if_variable name="sectorSideOverride" comparator="GREATER_EQUAL" value="1.0" />
    <set_variable name="sectorSide" value="sectorSideOverride" integer="yes" />
    <set_variable name="System Settings" value="3.0" integer="yes" />
  </event>
  <event name="Sector Side Override (RESET)" id_arme="6e959c03-0cf4-4896-8370-708ee5d520b5" parent_id_arme="f3c59cb5-0313-4447-af42-86dc6c1feffd">
    <if_variable name="System Settings" comparator="EQUALS" value="3.0" />
    <set_variable name="sectorSideOverride" value="0.0" integer="yes" />
    <set_variable name="System Settings" value="0.0" integer="yes" />
  </event>
  <event name="Set Sector Side" id_arme="f729a094-5131-48f9-a880-07becef4410b" parent_id_arme="f3c59cb5-0313-4447-af42-86dc6c1feffd">
    <if_variable name="System Settings" comparator="EQUALS" value="2.0" />
    <if_variable name="Sierra System" comparator="EQUALS" value="System" />
    <if_variable name="sectorSideOverride" comparator="LESS" value="1.0" />
    <set_variable name="sectorSide" value="systemSide" integer="yes" />
    <set_variable name="System Settings" value="0.0" integer="yes" />
  </event>
  <folder_arme name="Sierra Sector I" id_arme="149797a5-217d-4d03-9e23-ea8ea51c2828" parent_id_arme="e9246d5c-950d-4fec-a3ee-d076de7edef0" />
  <event name="Create Sierra Sector I" id_arme="356416f6-ee89-4d6b-85f8-ebc8a097ee26" parent_id_arme="149797a5-217d-4d03-9e23-ea8ea51c2828">
    <if_variable name="Sierra System" comparator="EQUALS" value="1.0" />
    <if_variable name="Sector" comparator="EQUALS" value="1.0" />
    <if_timer_finished name="Transition" />
    <set_skybox_index index="26" />
    <set_variable name="Sector Entities" value="1.0" />
    <set_variable name="Sierra System" value="2.0" />
    <set_variable name="Grid 5 Transition Enabled" value="1.0" />
    <set_variable name="Grid 1 Transition Enabled" value="0.0" />
    <set_variable name="Grid E Transition Enabled" value="1.0" />
    <set_variable name="Grid A Transition Enabled" value="0.0" />
    <set_variable name="Corner A1 Transition Enabled" value="0.0" />
    <set_variable name="Corner A5 Transition Enabled" value="0.0" />
    <set_variable name="Corner E1 Transition Enabled" value="0.0" />
    <set_variable name="Corner E5 Transition Enabled" value="1.0" />
    <create count="50" type="nebulas" startX="70532.0" startY="0.0" startZ="32358.0" endX="70532.0" endY="0.0" endZ="32358.0" randomRange="17500" randomSeed="45" />
    <create count="50" type="nebulas" startX="62060.0" startY="0.0" startZ="15215.0" endX="18605.0" endY="0.0" endZ="37840.0" randomRange="4638" />
    <create count="7" type="mines" startX="47808.0" startY="0.0" startZ="49401.0" endX="47808.0" endY="0.0" endZ="49401.0" randomRange="45000" />
    <create count="150" type="asteroids" startX="52094.0" startY="0.0" startZ="32857.0" endX="17000.0" endY="0.0" endZ="55000.0" randomRange="15000" />
    <create count="25" type="nebulas" startX="55000.0" startY="0.0" startZ="73000.0" endX="26778.0" endY="0.0" endZ="88073.0" randomRange="4638" />
  </event>
  <folder_arme name="Navigation" id_arme="e169324d-0997-4c9a-8413-6c6abbfd5582" parent_id_arme="149797a5-217d-4d03-9e23-ea8ea51c2828" />
  <event name="Transition to Sector II" id_arme="8ec81d16-8284-4f9f-bdcd-2a49fc419506" parent_id_arme="e169324d-0997-4c9a-8413-6c6abbfd5582">
    <if_variable name="Sierra System" comparator="EQUALS" value="2.0" />
    <if_variable name="Sector" comparator="EQUALS" value="1.0" />
    <if_variable name="Grid 5 Transition" comparator="EQUALS" value="1.0" />
    <warning_popup_message message="Sector Transition" consoles="MHWESCO">Sector Transition in progress</warning_popup_message>
    <destroy_near type="all" radius="100000" centerX="50000" centerY="0" centerZ="50000" />
    <set_timer name="Transition" seconds="0.5" />
    <set_variable name="Grid 5 Transition" value="0.0" />
    <set_variable name="Sector" value="2.0" integer="yes" />
    <set_variable name="Sierra System" value="3.0" integer="yes" />
  </event>
  <event name="Transition to Sector IV" id_arme="dcfeb439-18e5-4c3f-ba37-e7132c4e31da" parent_id_arme="e169324d-0997-4c9a-8413-6c6abbfd5582">
    <if_variable name="Grid E Transition" comparator="EQUALS" value="1.0" />
    <if_variable name="Sector" comparator="EQUALS" value="1.0" />
    <if_variable name="Sierra System" comparator="EQUALS" value="2.0" />
    <warning_popup_message message="Sector Transition" consoles="MHWESCO">Sector Transition in progress</warning_popup_message>
    <destroy_near type="all" radius="100000" centerX="50000" centerY="0" centerZ="50000" />
    <set_variable name="Sector" value="4.0" integer="yes" />
    <set_variable name="Sierra System" value="3.0" integer="yes" />
    <set_timer name="Transition" seconds="0.5" />
    <set_variable name="Grid E Transition" value="0.0" />
  </event>
  <event name="Transition to (Bottom Right)" id_arme="a64712a7-7456-4aa0-b510-70981b4a91b8" parent_id_arme="e169324d-0997-4c9a-8413-6c6abbfd5582">
    <if_variable name="Corner E5 Transition" comparator="EQUALS" value="1.0" />
    <if_variable name="Sierra System" comparator="EQUALS" value="2.0" />
    <if_variable name="Sector" comparator="EQUALS" value="1.0" />
    <warning_popup_message message="Sector Transition" consoles="MHWESCO">Sector Transition in progress</warning_popup_message>
    <destroy_near type="all" radius="100000" centerX="50000" centerY="0" centerZ="50000" />
    <set_variable name="Sierra System" value="3.0" integer="yes" />
    <set_variable name="Sector" value="5.0" integer="yes" />
    <set_timer name="Transition" seconds="0.5" />
    <set_variable name="Corner E5 Transition" value="0.0" />
  </event>
  <folder_arme name="Sector Entities" id_arme="3fb2d211-63c3-4959-ab12-e9bfcbe29aa4" parent_id_arme="149797a5-217d-4d03-9e23-ea8ea51c2828" />
  <event name="Generate Sector Entities" id_arme="8064f695-f799-4a82-b94c-7ff40955ed68" parent_id_arme="3fb2d211-63c3-4959-ab12-e9bfcbe29aa4">
    <if_variable name="Sierra System" comparator="EQUALS" value="2.0" />
    <if_variable name="Sector" comparator="EQUALS" value="1.0" />
    <if_variable name="Sector Entities" comparator="EQUALS" value="1.0" />
    <set_variable name="ExitorRetreat" value="0.0" />
    <set_variable name="Sector Entities" value="2.0" />
    <set_variable name="MissionCode" value="1.0" />
  </event>
  <event name="Settings" id_arme="7ce8b71a-5803-4777-98f8-3356a6ee8064" parent_id_arme="3fb2d211-63c3-4959-ab12-e9bfcbe29aa4">
    <if_variable name="Sierra System" comparator="EQUALS" value="2.0" />
    <if_variable name="Sector" comparator="EQUALS" value="1.0" />
    <if_variable name="Sector Entities" comparator="EQUALS" value="2.0" />
    <set_variable name="Sector Entities" value="3.0" />
  </event>
  <event name="Destroy Sector Entities" id_arme="306c762d-a28a-4446-a3a1-cef53227afa5" parent_id_arme="3fb2d211-63c3-4959-ab12-e9bfcbe29aa4">
    <if_variable name="Sierra System" comparator="EQUALS" value="3.0" />
    <set_variable name="Sierra System" value="System" integer="yes" />
    <set_variable name="Sector Entities" value="0.0" />
  </event>
  <folder_arme name="Sierra Sector II" id_arme="9b5a6ebc-274a-42ec-9fc7-eff67bffcbaf" parent_id_arme="e9246d5c-950d-4fec-a3ee-d076de7edef0" />
  <event name="Create Sierra Sector II" id_arme="6e8a6f42-7123-48ae-88ee-b64a9dd08366" parent_id_arme="9b5a6ebc-274a-42ec-9fc7-eff67bffcbaf">
    <if_variable name="Sierra System" comparator="EQUALS" value="1.0" />
    <if_variable name="Sector" comparator="EQUALS" value="2.0" />
    <if_timer_finished name="Transition" />
    <set_skybox_index index="26" />
    <set_variable name="Sector Entities" value="1.0" />
    <set_variable name="Sierra System" value="2.0" />
    <set_variable name="Grid 5 Transition Enabled" value="1.0" />
    <set_variable name="Grid 1 Transition Enabled" value="1.0" />
    <set_variable name="Grid E Transition Enabled" value="1.0" />
    <set_variable name="Grid A Transition Enabled" value="0.0" />
    <set_variable name="Corner A1 Transition Enabled" value="0.0" />
    <set_variable name="Corner A5 Transition Enabled" value="0.0" />
    <set_variable name="Corner E1 Transition Enabled" value="1.0" />
    <set_variable name="Corner E5 Transition Enabled" value="1.0" />
    <create count="50" type="nebulas" startX="62060.0" startY="0.0" startZ="15215.0" endX="18605.0" endY="0.0" endZ="37840.0" randomRange="4638" />
    <create count="7" type="mines" startX="47808.0" startY="0.0" startZ="49401.0" endX="47808.0" endY="0.0" endZ="49401.0" randomRange="45000" />
    <create count="150" type="asteroids" startX="71030.0" startY="0.0" startZ="65747.0" endX="17000.0" endY="0.0" endZ="55000.0" randomRange="24975" />
    <create count="25" type="nebulas" startX="55000.0" startY="0.0" startZ="73000.0" endX="26778.0" endY="0.0" endZ="88073.0" randomRange="4638" />
  </event>
  <folder_arme name="Navigation" id_arme="4bec2e69-b4bf-4a6f-8dbe-04138865d3ee" parent_id_arme="9b5a6ebc-274a-42ec-9fc7-eff67bffcbaf" />
  <event name="Transition to Sector III" id_arme="334396ed-1f6c-4881-ae3e-7ff19c4a0e91" parent_id_arme="4bec2e69-b4bf-4a6f-8dbe-04138865d3ee">
    <if_variable name="Grid 5 Transition" comparator="EQUALS" value="1.0" />
    <if_variable name="Sector" comparator="EQUALS" value="2.0" />
    <if_variable name="Sierra System" comparator="EQUALS" value="2.0" />
    <warning_popup_message message="Sector Transition" consoles="MHWESCO">Sector Transition in progress</warning_popup_message>
    <destroy_near type="all" radius="100000" centerX="50000" centerY="0" centerZ="50000" />
    <set_timer name="Transition" seconds="0.5" />
    <set_variable name="Grid 5 Transition" value="0.0" />
    <set_variable name="Sector" value="3.0" integer="yes" />
    <set_variable name="Sierra System" value="3.0" integer="yes" />
  </event>
  <event name="Transition to Sector I" id_arme="92fbf857-d1e0-41d3-856a-f8bdb238836e" parent_id_arme="4bec2e69-b4bf-4a6f-8dbe-04138865d3ee">
    <if_variable name="Grid 1 Transition" comparator="EQUALS" value="1.0" />
    <if_variable name="Sector" comparator="EQUALS" value="2.0" />
    <if_variable name="Sierra System" comparator="EQUALS" value="2.0" />
    <warning_popup_message message="Sector Transition" consoles="MHWESCO">Sector Transition in progress</warning_popup_message>
    <destroy_near type="all" radius="100000" centerX="50000" centerY="0" centerZ="50000" />
    <set_timer name="Transition" seconds="0.5" />
    <set_variable name="Grid 1 Transition" value="0.0" />
    <set_variable name="Sector" value="1.0" integer="yes" />
    <set_variable name="Sierra System" value="3.0" integer="yes" />
  </event>
  <event name="Transition to Sector V" id_arme="929ebe5f-a841-4696-8211-0981115a76b5" parent_id_arme="4bec2e69-b4bf-4a6f-8dbe-04138865d3ee">
    <if_variable name="Grid E Transition" comparator="EQUALS" value="1.0" />
    <if_variable name="Sector" comparator="EQUALS" value="2.0" />
    <if_variable name="Sierra System" comparator="EQUALS" value="2.0" />
    <warning_popup_message message="Sector Transition" consoles="MHWESCO">Sector Transition in progress</warning_popup_message>
    <destroy_near type="all" radius="100000" centerX="50000" centerY="0" centerZ="50000" />
    <set_timer name="Transition" seconds="0.5" />
    <set_variable name="Grid E Transition" value="0.0" />
    <set_variable name="Sector" value="5.0" integer="yes" />
    <set_variable name="Sierra System" value="3.0" integer="yes" />
  </event>
  <event name="Transition to (Bottom Right)" id_arme="077ba768-1a84-4e9e-8052-074ccbacfb5f" parent_id_arme="4bec2e69-b4bf-4a6f-8dbe-04138865d3ee">
    <if_variable name="Corner E5 Transition" comparator="EQUALS" value="1.0" />
    <if_variable name="Sector" comparator="EQUALS" value="2.0" />
    <if_variable name="Sierra System" comparator="EQUALS" value="2.0" />
    <warning_popup_message message="Sector Transition" consoles="MHWESCO">Sector Transition in progress</warning_popup_message>
    <destroy_near type="all" radius="100000" centerX="50000" centerY="0" centerZ="50000" />
    <set_timer name="Transition" seconds="0.5" />
    <set_variable name="Corner E5 Transition" value="0.0" />
    <set_variable name="Sierra System" value="3.0" integer="yes" />
    <set_variable name="Sector" value="6.0" integer="yes" />
  </event>
  <event name="Transition to (Bottom Left)" id_arme="f7c71616-c525-419c-adf7-c9594129265c" parent_id_arme="4bec2e69-b4bf-4a6f-8dbe-04138865d3ee">
    <if_variable name="Corner E1 Transition" comparator="EQUALS" value="1.0" />
    <if_variable name="Sector" comparator="EQUALS" value="2.0" />
    <if_variable name="Sierra System" comparator="EQUALS" value="2.0" />
    <warning_popup_message message="Sector Transition" consoles="MHWESCO">Sector Transition in progress</warning_popup_message>
    <destroy_near type="all" radius="100000" centerX="50000" centerY="0" centerZ="50000" />
    <set_timer name="Transition" seconds="0.5" />
    <set_variable name="Corner E1 Transition" value="0.0" />
    <set_variable name="Sierra System" value="3.0" integer="yes" />
    <set_variable name="Sector" value="4.0" integer="yes" />
  </event>
  <folder_arme name="System - Jump Gate Settings" id_arme="c6928acc-586a-4af6-b259-2eb1d94d9b4c" parent_id_arme="4bec2e69-b4bf-4a6f-8dbe-04138865d3ee" />
  <event name="Gate Offline" id_arme="caefcf16-7aaf-4ab0-9e62-f55dacf3af2b" parent_id_arme="c6928acc-586a-4af6-b259-2eb1d94d9b4c">
    <if_variable name="Sector" comparator="EQUALS" value="2" />
    <if_variable name="Sierra System" comparator="EQUALS" value="2.0" />
    <if_variable name="Gate System" comparator="EQUALS" value="0.0" />
    <set_object_property property="rollDelta" value="0.3" name="Erebus Gate" />
  </event>
  <folder_arme name="Tracking System" id_arme="6cd9ff78-6708-4148-b291-6ad42c75d824" parent_id_arme="c6928acc-586a-4af6-b259-2eb1d94d9b4c" />
  <event name="Ship1 Activation Range" id_arme="379c24a0-2050-47ee-b182-295a3989c8a9" parent_id_arme="6cd9ff78-6708-4148-b291-6ad42c75d824">
    <if_variable name="Sector" comparator="EQUALS" value="2" />
    <if_variable name="Sierra System" comparator="EQUALS" value="2.0" />
    <if_variable name="Gate Tracking Ship1" comparator="EQUALS" value="0.0" />
    <if_distance player_slot1="0" name2="Erebus Gate" comparator="LESS" value="4000.0" />
    <if_variable name="Erebus Gate" comparator="EQUALS" value="1.0" />
    <set_variable name="shipsInrange" value="shipsInrange+1" />
    <set_variable name="Gate Tracking Ship1" value="1.0" />
  </event>
  <event name="Ship1 Out of Range" id_arme="65df09e4-a58e-4f80-a3ff-d5b276260deb" parent_id_arme="6cd9ff78-6708-4148-b291-6ad42c75d824">
    <if_variable name="Sector" comparator="EQUALS" value="2" />
    <if_variable name="Sierra System" comparator="EQUALS" value="2.0" />
    <if_variable name="Gate Tracking Ship1" comparator="EQUALS" value="1.0" />
    <if_distance player_slot1="0" name2="Erebus Gate" comparator="GREATER" value="4000.0" />
    <if_variable name="Erebus Gate" comparator="EQUALS" value="1.0" />
    <set_variable name="shipsInrange" value="shipsInrange-1" />
    <set_variable name="Gate Tracking Ship1" value="0.0" />
  </event>
  <event name="Ship2 Activation Range" id_arme="e0341846-e01a-4fe6-a615-ea0c23b54db8" parent_id_arme="6cd9ff78-6708-4148-b291-6ad42c75d824">
    <if_variable name="Sector" comparator="EQUALS" value="2" />
    <if_variable name="Sierra System" comparator="EQUALS" value="2.0" />
    <if_variable name="Gate Tracking Ship2" comparator="EQUALS" value="0.0" />
    <if_distance player_slot1="1" name2="Erebus Gate" comparator="LESS" value="4000.0" />
    <if_variable name="Erebus Gate" comparator="EQUALS" value="1.0" />
    <set_variable name="shipsInrange" value="shipsInrange+1" />
    <set_variable name="Gate Tracking Ship2" value="1.0" />
  </event>
  <event name="Ship2 Out of Range" id_arme="8baeec64-8ef3-42fd-8806-918b679a98b6" parent_id_arme="6cd9ff78-6708-4148-b291-6ad42c75d824">
    <if_variable name="Sector" comparator="EQUALS" value="2" />
    <if_variable name="Sierra System" comparator="EQUALS" value="2.0" />
    <if_variable name="Gate Tracking Ship2" comparator="EQUALS" value="1.0" />
    <if_distance player_slot1="1" name2="Erebus Gate" comparator="GREATER" value="4000.0" />
    <if_variable name="Erebus Gate" comparator="EQUALS" value="1.0" />
    <set_variable name="shipsInrange" value="shipsInrange-1" />
    <set_variable name="Gate Tracking Ship2" value="0.0" />
  </event>
  <event name="Ship3 Activation Range" id_arme="050f0f5e-8229-49df-b275-26570ed8b17e" parent_id_arme="6cd9ff78-6708-4148-b291-6ad42c75d824">
    <if_variable name="Sector" comparator="EQUALS" value="2" />
    <if_variable name="Sierra System" comparator="EQUALS" value="2.0" />
    <if_variable name="Gate Tracking Ship3" comparator="EQUALS" value="0.0" />
    <if_distance player_slot1="2" name2="Erebus Gate" comparator="LESS" value="4000.0" />
    <if_variable name="Erebus Gate" comparator="EQUALS" value="1.0" />
    <set_variable name="shipsInrange" value="shipsInrange+1" />
    <set_variable name="Gate Tracking Ship3" value="1.0" />
  </event>
  <event name="Ship3 Out of Range" id_arme="f2877b02-8506-4a81-b70e-c2500cee4a71" parent_id_arme="6cd9ff78-6708-4148-b291-6ad42c75d824">
    <if_variable name="Sector" comparator="EQUALS" value="2" />
    <if_variable name="Sierra System" comparator="EQUALS" value="2.0" />
    <if_variable name="Gate Tracking Ship3" comparator="EQUALS" value="1.0" />
    <if_distance player_slot1="2" name2="Erebus Gate" comparator="GREATER" value="4000.0" />
    <if_variable name="Erebus Gate" comparator="EQUALS" value="1.0" />
    <set_variable name="shipsInrange" value="shipsInrange-1" />
    <set_variable name="Gate Tracking Ship3" value="0.0" />
  </event>
  <event name="Ship4 Activation Range" id_arme="395192d8-3483-4667-9d3c-88741e77c812" parent_id_arme="6cd9ff78-6708-4148-b291-6ad42c75d824">
    <if_variable name="Sector" comparator="EQUALS" value="2" />
    <if_variable name="Sierra System" comparator="EQUALS" value="2.0" />
    <if_variable name="Gate Tracking Ship4" comparator="EQUALS" value="0.0" />
    <if_distance player_slot1="3" name2="Erebus Gate" comparator="LESS" value="4000.0" />
    <if_variable name="Erebus Gate" comparator="EQUALS" value="1.0" />
    <set_variable name="shipsInrange" value="shipsInrange+1" />
    <set_variable name="Gate Tracking Ship4" value="1.0" />
  </event>
  <event name="Ship4 Out of Range" id_arme="78d2f3b9-bb60-45a1-ae0c-0bcfa0a87924" parent_id_arme="6cd9ff78-6708-4148-b291-6ad42c75d824">
    <if_variable name="Sector" comparator="EQUALS" value="2" />
    <if_variable name="Sierra System" comparator="EQUALS" value="2.0" />
    <if_variable name="Gate Tracking Ship4" comparator="EQUALS" value="1.0" />
    <if_distance player_slot1="3" name2="Erebus Gate" comparator="GREATER" value="4000.0" />
    <if_variable name="Erebus Gate" comparator="EQUALS" value="1.0" />
    <set_variable name="shipsInrange" value="shipsInrange-1" />
    <set_variable name="Gate Tracking Ship4" value="0.0" />
  </event>
  <event name="Ship5 Activation Range" id_arme="0d39d1a6-1267-4a90-8144-d01cf82fdf37" parent_id_arme="6cd9ff78-6708-4148-b291-6ad42c75d824">
    <if_variable name="Sector" comparator="EQUALS" value="2" />
    <if_variable name="Sierra System" comparator="EQUALS" value="2.0" />
    <if_variable name="Gate Tracking Ship5" comparator="EQUALS" value="0.0" />
    <if_distance player_slot1="4" name2="Erebus Gate" comparator="LESS" value="4000.0" />
    <if_variable name="Erebus Gate" comparator="EQUALS" value="1.0" />
    <set_variable name="shipsInrange" value="shipsInrange+1" />
    <set_variable name="Gate Tracking Ship5" value="1.0" />
  </event>
  <event name="Ship5 Out of Range" id_arme="258252a1-d49e-4ebf-98b2-f7b450c6c078" parent_id_arme="6cd9ff78-6708-4148-b291-6ad42c75d824">
    <if_variable name="Sector" comparator="EQUALS" value="2" />
    <if_variable name="Sierra System" comparator="EQUALS" value="2.0" />
    <if_variable name="Gate Tracking Ship5" comparator="EQUALS" value="1.0" />
    <if_distance player_slot1="4" name2="Erebus Gate" comparator="GREATER" value="4000.0" />
    <if_variable name="Erebus Gate" comparator="EQUALS" value="1.0" />
    <set_variable name="shipsInrange" value="shipsInrange-1" />
    <set_variable name="Gate Tracking Ship5" value="0.0" />
  </event>
  <event name="Ship6 Activation Range" id_arme="eb1cef24-1082-48a2-9fa6-32559219d9d3" parent_id_arme="6cd9ff78-6708-4148-b291-6ad42c75d824">
    <if_variable name="Sector" comparator="EQUALS" value="2" />
    <if_variable name="Sierra System" comparator="EQUALS" value="2.0" />
    <if_variable name="Gate Tracking Ship6" comparator="EQUALS" value="0.0" />
    <if_distance player_slot1="5" name2="Erebus Gate" comparator="LESS" value="4000.0" />
    <if_variable name="Erebus Gate" comparator="EQUALS" value="1.0" />
    <set_variable name="shipsInrange" value="shipsInrange+1" />
    <set_variable name="Gate Tracking Ship6" value="1.0" />
  </event>
  <event name="Ship6 Out of Range" id_arme="8bf63230-3dfa-442d-b0f2-d449fa12f2cc" parent_id_arme="6cd9ff78-6708-4148-b291-6ad42c75d824">
    <if_variable name="Sector" comparator="EQUALS" value="2" />
    <if_variable name="Sierra System" comparator="EQUALS" value="2.0" />
    <if_variable name="Gate Tracking Ship6" comparator="EQUALS" value="1.0" />
    <if_distance player_slot1="5" name2="Erebus Gate" comparator="GREATER" value="4000.0" />
    <if_variable name="Erebus Gate" comparator="EQUALS" value="1.0" />
    <set_variable name="shipsInrange" value="shipsInrange-1" />
    <set_variable name="Gate Tracking Ship6" value="0.0" />
  </event>
  <event name="Ship7 Activation Range" id_arme="8a2bca4f-6a42-4177-bbd5-1add5b093d22" parent_id_arme="6cd9ff78-6708-4148-b291-6ad42c75d824">
    <if_variable name="Sector" comparator="EQUALS" value="2" />
    <if_variable name="Sierra System" comparator="EQUALS" value="2.0" />
    <if_variable name="Gate Tracking Ship7" comparator="EQUALS" value="0.0" />
    <if_distance player_slot1="6" name2="Erebus Gate" comparator="LESS" value="4000.0" />
    <if_variable name="Erebus Gate" comparator="EQUALS" value="1.0" />
    <set_variable name="shipsInrange" value="shipsInrange+1" />
    <set_variable name="Gate Tracking Ship7" value="1.0" />
  </event>
  <event name="Ship7 Out of Range" id_arme="6d2e4f7a-e36f-4e96-8130-f279b6a79457" parent_id_arme="6cd9ff78-6708-4148-b291-6ad42c75d824">
    <if_variable name="Sector" comparator="EQUALS" value="2" />
    <if_variable name="Sierra System" comparator="EQUALS" value="2.0" />
    <if_variable name="Gate Tracking Ship7" comparator="EQUALS" value="1.0" />
    <if_distance player_slot1="6" name2="Erebus Gate" comparator="GREATER" value="4000.0" />
    <if_variable name="Erebus Gate" comparator="EQUALS" value="1.0" />
    <set_variable name="shipsInrange" value="shipsInrange-1" />
    <set_variable name="Gate Tracking Ship7" value="0.0" />
  </event>
  <event name="Ship8 Activation Range" id_arme="4c9d13c7-2750-47b3-9521-83cae98a70dc" parent_id_arme="6cd9ff78-6708-4148-b291-6ad42c75d824">
    <if_variable name="Sector" comparator="EQUALS" value="2" />
    <if_variable name="Sierra System" comparator="EQUALS" value="2.0" />
    <if_variable name="Gate Tracking Ship8" comparator="EQUALS" value="0.0" />
    <if_distance player_slot1="7" name2="Erebus Gate" comparator="LESS" value="4000.0" />
    <if_variable name="Erebus Gate" comparator="EQUALS" value="1.0" />
    <set_variable name="shipsInrange" value="shipsInrange+1" />
    <set_variable name="Gate Tracking Ship8" value="1.0" />
  </event>
  <event name="Ship8 Out of Range" id_arme="d4369f52-2861-48ea-ad96-f8c30d7aeb18" parent_id_arme="6cd9ff78-6708-4148-b291-6ad42c75d824">
    <if_variable name="Sector" comparator="EQUALS" value="2" />
    <if_variable name="Sierra System" comparator="EQUALS" value="2.0" />
    <if_variable name="Gate Tracking Ship8" comparator="EQUALS" value="1.0" />
    <if_distance player_slot1="7" name2="Erebus Gate" comparator="GREATER" value="4000.0" />
    <if_variable name="Erebus Gate" comparator="EQUALS" value="1.0" />
    <set_variable name="shipsInrange" value="shipsInrange-1" />
    <set_variable name="Gate Tracking Ship8" value="0.0" />
  </event>
  <event name="Gate Online" id_arme="f326b9c6-719b-4209-860c-87cb84b5f15c" parent_id_arme="c6928acc-586a-4af6-b259-2eb1d94d9b4c">
    <if_variable name="Sector" comparator="EQUALS" value="2" />
    <if_variable name="Sierra System" comparator="EQUALS" value="2.0" />
    <if_variable name="Gate System" comparator="EQUALS" value="1.0" />
    <if_comms_button text="Activate Gate" />
    <if_variable name="Erebus Gate" comparator="EQUALS" value="1.0" />
    <incoming_comms_text from="Gate System" sideValue="playerSide" type="STATUS">Activating Gate^Locking signal...</incoming_comms_text>
    <set_object_property property="rollDelta" value="1.0" name="Erebus Gate" />
    <set_timer name="Gate System" seconds="5" />
    <set_variable name="Gate System" value="2.0" />
    <clear_comms_button text="Activate Gate" sideValue="playerSide" />
  </event>
  <event name="Jump Initiated" id_arme="8795135a-12de-4761-86f1-1b4c819bdf17" parent_id_arme="c6928acc-586a-4af6-b259-2eb1d94d9b4c">
    <if_variable name="Sector" comparator="EQUALS" value="2" />
    <if_variable name="Sierra System" comparator="EQUALS" value="2.0" />
    <if_comms_button text="Jump" />
    <if_variable name="Gate System" comparator="EQUALS" value="3.0" />
    <if_variable name="Erebus Gate" comparator="EQUALS" value="1.0" />
    <clear_comms_button text="Jump" sideValue="playerSide" />
    <set_variable name="Sierra System" value="3.0" integer="yes" />
    <set_variable name="System" value="0.0" />
    <destroy_near type="all" radius="100000" centerX="50000" centerY="0" centerZ="50000" />
    <set_variable name="Sierra to Erebus" value="1.0" />
    <set_variable name="Erebus System" value="1.0" />
    <set_variable name="shipsInrange" value="0.0" integer="yes" />
    <set_variable name="Sector" value="10" />
    <set_timer name="Transition" seconds="2" />
    <set_variable name="Gate System" value="0.0" />
    <set_variable name="ExitorRetreat" value="1.0" />
  </event>
  <folder_arme name="Sector Entities" id_arme="25996515-1a01-4a1c-b358-8b0424cb9499" parent_id_arme="9b5a6ebc-274a-42ec-9fc7-eff67bffcbaf" />
  <event name="Generate Sector Entities" id_arme="ca9aab58-9ef1-4594-8578-02d51f9af0cb" parent_id_arme="25996515-1a01-4a1c-b358-8b0424cb9499">
    <if_variable name="Sierra System" comparator="EQUALS" value="2.0" />
    <if_variable name="Sector" comparator="EQUALS" value="2.0" />
    <if_variable name="Sector Entities" comparator="EQUALS" value="1.0" />
    <create type="genericMesh" x="53959.0" y="0.0" z="28450.0" name="Erebus Gate" meshFileName="dat\TSN\USFP\TSNGate.dxs" textureFileName="dat\TSN\USFP\TSNGate.png" colorRed="1.0" colorGreen="0.5" colorBlue="0.0" />
    <set_variable name="ExitorRetreat" value="0.0" />
    <set_variable name="Sector Entities" value="2.0" />
    <set_variable name="MissionCode" value="1.0" />
  </event>
  <event name="Settings" id_arme="e0078c05-0b45-43b1-ac52-7e535fa0fbda" parent_id_arme="25996515-1a01-4a1c-b358-8b0424cb9499">
    <if_variable name="Sector" comparator="EQUALS" value="2.0" />
    <if_variable name="Sierra System" comparator="EQUALS" value="2.0" />
    <if_variable name="Sector Entities" comparator="EQUALS" value="2.0" />
    <set_object_property property="artScale" value="1.0" name="Erebus Gate" />
    <set_object_property property="pushRadius" value="0.0" name="Erebus Gate" />
    <set_object_property property="angle" value="4.71238898" name="Erebus Gate" />
    <set_object_property property="rollDelta" value="0.3" name="Erebus Gate" />
    <set_variable name="Sector Entities" value="3.0" />
  </event>
  <event name="Destroy Sector Entities" id_arme="29f0ef4b-8364-489a-837f-bfe63a0692ea" parent_id_arme="25996515-1a01-4a1c-b358-8b0424cb9499">
    <if_variable name="Sierra System" comparator="EQUALS" value="3.0" />
    <destroy name="Erebus Gate" />
    <set_variable name="Sierra System" value="System" integer="yes" />
    <set_variable name="Sector Entities" value="0.0" />
  </event>
  <event name="Arrival From Erebus" id_arme="7562c642-0290-4eba-9321-83965faf0997" parent_id_arme="9b5a6ebc-274a-42ec-9fc7-eff67bffcbaf">
    <if_variable name="Sector" comparator="EQUALS" value="2" />
    <if_variable name="Sierra System" comparator="EQUALS" value="2.0" />
    <if_variable name="Erebus to Sierra" comparator="EQUALS" value="1.0" />
    <if_timer_finished name="Transition" />
    <set_relative_position player_slot2="0" distance="4200" angle="0.0" name1="Erebus Gate" />
    <set_relative_position player_slot2="1" distance="4200" angle="5.0" name1="Erebus Gate" />
    <set_relative_position player_slot2="2" distance="4200" angle="10.0" name1="Erebus Gate" />
    <set_relative_position player_slot2="3" distance="4200" angle="15.0" name1="Erebus Gate" />
    <set_relative_position player_slot2="4" distance="4200" angle="20.0" name1="Erebus Gate" />
    <set_relative_position player_slot2="5" distance="4200" angle="355.0" name1="Erebus Gate" />
    <set_relative_position player_slot2="6" distance="4200" angle="350.0" name1="Erebus Gate" />
    <set_relative_position player_slot2="7" distance="4200" angle="345.0" name1="Erebus Gate" />
    <set_object_property property="angle" value="3.141592654" player_slot="0" />
    <set_object_property property="angle" value="3.141592654" player_slot="1" />
    <set_object_property property="angle" value="3.141592654" player_slot="2" />
    <set_object_property property="angle" value="3.141592654" player_slot="3" />
    <set_object_property property="angle" value="3.141592654" player_slot="4" />
    <set_object_property property="angle" value="3.141592654" player_slot="5" />
    <set_object_property property="angle" value="3.141592654" player_slot="6" />
    <set_object_property property="angle" value="3.141592654" player_slot="7" />
    <set_variable name="Erebus to Sierra" value="0.0" />
  </event>
  <folder_arme name="Sierra Sector III" id_arme="46ea092e-1f2f-4bad-a4ac-e5c8310bef26" parent_id_arme="e9246d5c-950d-4fec-a3ee-d076de7edef0" />
  <event name="Create Sierra Sector III" id_arme="1362fcad-6a0a-4d19-9817-03aeec15cbc4" parent_id_arme="46ea092e-1f2f-4bad-a4ac-e5c8310bef26">
    <if_variable name="Sierra System" comparator="EQUALS" value="1.0" />
    <if_variable name="Sector" comparator="EQUALS" value="3.0" />
    <if_timer_finished name="Transition" />
    <set_skybox_index index="26" />
    <set_variable name="Sector Entities" value="1.0" />
    <set_variable name="Sierra System" value="2.0" />
    <set_variable name="Grid 5 Transition Enabled" value="0.0" />
    <set_variable name="Grid 1 Transition Enabled" value="1.0" />
    <set_variable name="Grid E Transition Enabled" value="1.0" />
    <set_variable name="Grid A Transition Enabled" value="0.0" />
    <set_variable name="Corner A1 Transition Enabled" value="0.0" />
    <set_variable name="Corner A5 Transition Enabled" value="0.0" />
    <set_variable name="Corner E1 Transition Enabled" value="1.0" />
    <set_variable name="Corner E5 Transition Enabled" value="0.0" />
    <create count="50" type="nebulas" startAngle="265" endAngle="354.9" startX="75814.0" startY="0.0" startZ="31760.0" radius="7000" randomRange="2500" />
    <create count="100" type="nebulas" startAngle="224.6" endAngle="345.6" startX="74519.0" startY="0.0" startZ="45714.0" radius="12500" randomRange="5000" />
    <create count="100" type="nebulas" startAngle="170.3" endAngle="289.4" startX="64353.0" startY="0.0" startZ="58770.0" radius="15000" randomRange="10659" />
    <create count="200" type="nebulas" startAngle="202.1" endAngle="100" startX="51994.0" startY="0.0" startZ="50398.0" radius="25000" randomRange="12519" />
  </event>
  <folder_arme name="Navigation" id_arme="6d59615a-0012-409b-b0af-cd0c17d2535f" parent_id_arme="46ea092e-1f2f-4bad-a4ac-e5c8310bef26" />
  <event name="Transition to Sector II" id_arme="163ad8bf-7e64-47fe-a6d0-ee55cf1f1f6a" parent_id_arme="6d59615a-0012-409b-b0af-cd0c17d2535f">
    <if_variable name="Grid 1 Transition" comparator="EQUALS" value="1.0" />
    <if_variable name="Sector" comparator="EQUALS" value="3.0" />
    <if_variable name="Sierra System" comparator="EQUALS" value="2.0" />
    <warning_popup_message message="Sector Transition" consoles="MHWESCO">Sector Transition in progress</warning_popup_message>
    <destroy_near type="all" radius="100000" centerX="50000" centerY="0" centerZ="50000" />
    <set_timer name="Transition" seconds="0.5" />
    <set_variable name="Grid 1 Transition" value="0.0" />
    <set_variable name="Sierra System" value="3.0" integer="yes" />
    <set_variable name="Sector" value="2.0" integer="yes" />
  </event>
  <event name="Transition to Sector VI" id_arme="a42a771f-8758-497e-978f-f5eac457358a" parent_id_arme="6d59615a-0012-409b-b0af-cd0c17d2535f">
    <if_variable name="Grid E Transition" comparator="EQUALS" value="1.0" />
    <if_variable name="Sierra System" comparator="EQUALS" value="2.0" />
    <if_variable name="Sector" comparator="EQUALS" value="3.0" />
    <warning_popup_message message="Sector Transition" consoles="MHWESCO">Sector Transition in progress</warning_popup_message>
    <destroy_near type="all" radius="100000" centerX="50000" centerY="0" centerZ="50000" />
    <set_timer name="Transition" seconds="0.5" />
    <set_variable name="Grid E Transition" value="0.0" />
    <set_variable name="Sierra System" value="3.0" integer="yes" />
    <set_variable name="Sector" value="6.0" integer="yes" />
  </event>
  <event name="Transition to (Bottom Left)" id_arme="b0e6ca9f-9395-4442-990e-f0f5be24da67" parent_id_arme="6d59615a-0012-409b-b0af-cd0c17d2535f">
    <if_variable name="Corner E1 Transition" comparator="EQUALS" value="1.0" />
    <if_variable name="Sierra System" comparator="EQUALS" value="2.0" />
    <if_variable name="Sector" comparator="EQUALS" value="3.0" />
    <warning_popup_message message="Sector Transition" consoles="MHWESCO">Sector Transition in progress</warning_popup_message>
    <destroy_near type="all" radius="100000" centerX="50000" centerY="0" centerZ="50000" />
    <set_timer name="Transition" seconds="0.5" />
    <set_variable name="Corner E1 Transition" value="0.0" />
    <set_variable name="Sierra System" value="3.0" integer="yes" />
    <set_variable name="Sector" value="5.0" integer="yes" />
  </event>
  <folder_arme name="Sector Entities" id_arme="31d5702c-c2ae-4d0d-bb70-e23a76b48c1c" parent_id_arme="46ea092e-1f2f-4bad-a4ac-e5c8310bef26" />
  <event name="Generate Sector Entities" id_arme="7ed76440-48ed-48d1-bbca-266a8675282e" parent_id_arme="31d5702c-c2ae-4d0d-bb70-e23a76b48c1c">
    <if_variable name="Sierra System" comparator="EQUALS" value="2.0" />
    <if_variable name="Sector" comparator="EQUALS" value="3.0" />
    <if_variable name="Sector Entities" comparator="EQUALS" value="1.0" />
    <create type="blackHole" x="74718.0" y="0.0" z="22890.0" name="Gertrude" />
    <set_variable name="ExitorRetreat" value="0.0" />
    <set_variable name="Sector Entities" value="2.0" />
    <set_variable name="MissionCode" value="1.0" />
  </event>
  <event name="Settings" id_arme="a261f1eb-60ef-41d8-8eff-ac5cc6b23991" parent_id_arme="31d5702c-c2ae-4d0d-bb70-e23a76b48c1c">
    <if_variable name="Sector" comparator="EQUALS" value="3.0" />
    <if_variable name="Sierra System" comparator="EQUALS" value="2.0" />
    <if_variable name="Sector Entities" comparator="EQUALS" value="2.0" />
    <set_variable name="Sector Entities" value="3.0" />
  </event>
  <event name="Destroy Sector Entities" id_arme="0019142b-9c15-4a5c-8e20-a5aed804e9bd" parent_id_arme="31d5702c-c2ae-4d0d-bb70-e23a76b48c1c">
    <if_variable name="Sierra System" comparator="EQUALS" value="3.0" />
    <destroy name="Gertrude" />
    <set_variable name="Sierra System" value="System" integer="yes" />
    <set_variable name="Sector Entities" value="0.0" />
  </event>
  <folder_arme name="Sierra Sector IV" id_arme="1e1cbc98-0a49-43d5-a845-c0cb0e7a6143" parent_id_arme="e9246d5c-950d-4fec-a3ee-d076de7edef0" />
  <event name="Create Sierra Sector IV" id_arme="d79b5ff3-0b9c-4d30-b74a-2baf79b502e3" parent_id_arme="1e1cbc98-0a49-43d5-a845-c0cb0e7a6143">
    <if_variable name="Sierra System" comparator="EQUALS" value="1.0" />
    <if_variable name="Sector" comparator="EQUALS" value="4.0" />
    <if_timer_finished name="Transition" />
    <set_skybox_index index="26" />
    <set_variable name="Sector Entities" value="1.0" />
    <set_variable name="Sierra System" value="2.0" />
    <set_variable name="Grid 5 Transition Enabled" value="1.0" />
    <set_variable name="Grid 1 Transition Enabled" value="0.0" />
    <set_variable name="Grid E Transition Enabled" value="1.0" />
    <set_variable name="Grid A Transition Enabled" value="1.0" />
    <set_variable name="Corner A1 Transition Enabled" value="0.0" />
    <set_variable name="Corner A5 Transition Enabled" value="1.0" />
    <set_variable name="Corner E1 Transition Enabled" value="0.0" />
    <set_variable name="Corner E5 Transition Enabled" value="1.0" />
    <create count="150" type="asteroids" startX="67542.0" startY="0.0" startZ="71727.0" endX="17000.0" endY="0.0" endZ="55000.0" randomRange="15000" />
    <create count="50" type="nebulas" startX="70233.0" startY="0.0" startZ="77109.0" endX="18605.0" endY="0.0" endZ="37840.0" randomRange="4638" />
  </event>
  <folder_arme name="Navigation" id_arme="cf8be423-bb3f-42d2-ae8f-e63e485e330c" parent_id_arme="1e1cbc98-0a49-43d5-a845-c0cb0e7a6143" />
  <event name="Transition to Sector V" id_arme="3aee7944-fd8b-4cf4-bd79-894c8d0a6618" parent_id_arme="cf8be423-bb3f-42d2-ae8f-e63e485e330c">
    <if_variable name="Grid 5 Transition" comparator="EQUALS" value="1.0" />
    <if_variable name="Sector" comparator="EQUALS" value="4.0" />
    <if_variable name="Sierra System" comparator="EQUALS" value="2.0" />
    <warning_popup_message message="Sector Transition" consoles="MHWESCO">Sector Transition in progress</warning_popup_message>
    <destroy_near type="all" radius="100000" centerX="50000" centerY="0" centerZ="50000" />
    <set_timer name="Transition" seconds="0.5" />
    <set_variable name="Grid 5 Transition" value="0.0" />
    <set_variable name="Sierra System" value="3.0" integer="yes" />
    <set_variable name="Sector" value="5.0" integer="yes" />
  </event>
  <event name="Transition to Sector I" id_arme="695137aa-5d98-4613-b547-09b628cc3f4c" parent_id_arme="cf8be423-bb3f-42d2-ae8f-e63e485e330c">
    <if_variable name="Grid A Transition" comparator="EQUALS" value="1.0" />
    <if_variable name="Sierra System" comparator="EQUALS" value="2.0" />
    <if_variable name="Sector" comparator="EQUALS" value="4.0" />
    <warning_popup_message message="Sector Transition" consoles="MHWESCO">Sector Transition in progress</warning_popup_message>
    <destroy_near type="all" radius="100000" centerX="50000" centerY="0" centerZ="50000" />
    <set_timer name="Transition" seconds="0.5" />
    <set_variable name="Grid A Transition" value="0.0" />
    <set_variable name="Sierra System" value="3.0" integer="yes" />
    <set_variable name="Sector" value="1.0" integer="yes" />
  </event>
  <event name="Transition to Sector VII" id_arme="3ee5bc85-8b2d-4b49-bbca-e8919a66df45" parent_id_arme="cf8be423-bb3f-42d2-ae8f-e63e485e330c">
    <if_variable name="Grid E Transition" comparator="EQUALS" value="1.0" />
    <if_variable name="Sierra System" comparator="EQUALS" value="2.0" />
    <if_variable name="Sector" comparator="EQUALS" value="4.0" />
    <warning_popup_message message="Sector Transition" consoles="MHWESCO">Sector Transition in progress</warning_popup_message>
    <destroy_near type="all" radius="100000" centerX="50000" centerY="0" centerZ="50000" />
    <set_timer name="Transition" seconds="0.5" />
    <set_variable name="Grid E Transition" value="0.0" />
    <set_variable name="Sierra System" value="3.0" integer="yes" />
    <set_variable name="Sector" value="7.0" integer="yes" />
  </event>
  <event name="Transition to (Bottom Right)" id_arme="d01b6adc-0e36-4520-afd2-dcfe9439d3e3" parent_id_arme="cf8be423-bb3f-42d2-ae8f-e63e485e330c">
    <if_variable name="Corner E5 Transition" comparator="EQUALS" value="1.0" />
    <if_variable name="Sierra System" comparator="EQUALS" value="2.0" />
    <if_variable name="Sector" comparator="EQUALS" value="4.0" />
    <warning_popup_message message="Sector Transition" consoles="MHWESCO">Sector Transition in progress</warning_popup_message>
    <destroy_near type="all" radius="100000" centerX="50000" centerY="0" centerZ="50000" />
    <set_timer name="Transition" seconds="0.5" />
    <set_variable name="Corner E5 Transition" value="0.0" />
    <set_variable name="Sierra System" value="3.0" integer="yes" />
    <set_variable name="Sector" value="8.0" integer="yes" />
  </event>
  <event name="Transition to (Top Right)" id_arme="bc75d777-fb61-4338-b3d6-6056bcf428e4" parent_id_arme="cf8be423-bb3f-42d2-ae8f-e63e485e330c">
    <if_variable name="Corner A5 Transition" comparator="EQUALS" value="1.0" />
    <if_variable name="Sierra System" comparator="EQUALS" value="2.0" />
    <if_variable name="Sector" comparator="EQUALS" value="4.0" />
    <warning_popup_message message="Sector Transition" consoles="MHWESCO">Sector Transition in progress</warning_popup_message>
    <destroy_near type="all" radius="100000" centerX="50000" centerY="0" centerZ="50000" />
    <set_timer name="Transition" seconds="0.5" />
    <set_variable name="Corner A5 Transition" value="0.0" />
    <set_variable name="Sierra System" value="3.0" integer="yes" />
    <set_variable name="Sector" value="2.0" integer="yes" />
  </event>
  <folder_arme name="Sector Entities" id_arme="e4d1d31d-6cb1-4d5e-9b77-b552a60dec95" parent_id_arme="1e1cbc98-0a49-43d5-a845-c0cb0e7a6143" />
  <event name="Generate Sector Entities" id_arme="c9873756-437f-40f0-8d19-28a7ff47e03b" parent_id_arme="e4d1d31d-6cb1-4d5e-9b77-b552a60dec95">
    <if_variable name="Sierra System" comparator="EQUALS" value="2.0" />
    <if_variable name="Sector" comparator="EQUALS" value="4.0" />
    <if_variable name="Sector Entities" comparator="EQUALS" value="1.0" />
    <set_variable name="ExitorRetreat" value="0.0" />
    <set_variable name="Sector Entities" value="2.0" />
    <set_variable name="MissionCode" value="1.0" />
  </event>
  <event name="Settings" id_arme="60c62746-3a91-4119-829b-2fcfa6fb4c30" parent_id_arme="e4d1d31d-6cb1-4d5e-9b77-b552a60dec95">
    <if_variable name="Sector" comparator="EQUALS" value="4.0" />
    <if_variable name="Sierra System" comparator="EQUALS" value="2.0" />
    <if_variable name="Sector Entities" comparator="EQUALS" value="2.0" />
    <set_variable name="Sector Entities" value="3.0" />
  </event>
  <event name="Destroy Sector Entities" id_arme="1ea841b6-2cc0-4cbc-8328-cb8b059bdbcc" parent_id_arme="e4d1d31d-6cb1-4d5e-9b77-b552a60dec95">
    <if_variable name="Sierra System" comparator="EQUALS" value="3.0" />
    <set_variable name="Sierra System" value="System" integer="yes" />
    <set_variable name="Sector Entities" value="0.0" />
  </event>
  <folder_arme name="Sierra Sector V" id_arme="5d993fd3-e769-4ed6-a339-601c87afe77a" parent_id_arme="e9246d5c-950d-4fec-a3ee-d076de7edef0" />
  <event name="Create Sierra Sector V" id_arme="70e9467f-6d06-41d6-8e97-1150388c0b60" parent_id_arme="5d993fd3-e769-4ed6-a339-601c87afe77a">
    <if_variable name="Sierra System" comparator="EQUALS" value="1.0" />
    <if_variable name="Sector" comparator="EQUALS" value="5.0" />
    <if_timer_finished name="Transition" />
    <set_skybox_index index="26" />
    <set_variable name="Sector Entities" value="1.0" />
    <set_variable name="Sierra System" value="2.0" />
    <set_variable name="Grid 5 Transition Enabled" value="1.0" />
    <set_variable name="Grid 1 Transition Enabled" value="1.0" />
    <set_variable name="Grid E Transition Enabled" value="1.0" />
    <set_variable name="Grid A Transition Enabled" value="1.0" />
    <set_variable name="Corner A1 Transition Enabled" value="1.0" />
    <set_variable name="Corner A5 Transition Enabled" value="1.0" />
    <set_variable name="Corner E1 Transition Enabled" value="1.0" />
    <set_variable name="Corner E5 Transition Enabled" value="1.0" />
    <create count="25" type="asteroids" startX="10000.0" startY="0.0" startZ="10000.0" endX="90000.0" endY="0.0" endZ="90000.0" randomRange="15000" randomSeed="45" />
    <create count="50" type="nebulas" startX="61363.0" startY="0.0" startZ="25282.0" endX="18605.0" endY="0.0" endZ="37840.0" randomRange="4638" />
    <create count="50" type="nebulas" startX="94353.0" startY="0.0" startZ="77707.0" endX="18605.0" endY="0.0" endZ="37840.0" randomRange="4638" />
  </event>
  <folder_arme name="Navigation" id_arme="30aea8c2-2865-45a9-9fb9-6733e45b8246" parent_id_arme="5d993fd3-e769-4ed6-a339-601c87afe77a" />
  <event name="Transition to Sector VI" id_arme="d40ced61-e7a5-4675-8c7a-ab6604c46ef1" parent_id_arme="30aea8c2-2865-45a9-9fb9-6733e45b8246">
    <if_variable name="Grid 5 Transition" comparator="EQUALS" value="1.0" />
    <if_variable name="Sector" comparator="EQUALS" value="5.0" />
    <if_variable name="Sierra System" comparator="EQUALS" value="2.0" />
    <warning_popup_message message="Sector Transition" consoles="MHWESCO">Sector Transition in progress</warning_popup_message>
    <destroy_near type="all" radius="100000" centerX="50000" centerY="0" centerZ="50000" />
    <set_timer name="Transition" seconds="0.5" />
    <set_variable name="Grid 5 Transition" value="0.0" />
    <set_variable name="Sierra System" value="3.0" integer="yes" />
    <set_variable name="Sector" value="6.0" integer="yes" />
  </event>
  <event name="Transition to Sector IV" id_arme="a88313bf-978e-4097-a863-6dfe4873324c" parent_id_arme="30aea8c2-2865-45a9-9fb9-6733e45b8246">
    <if_variable name="Grid 1 Transition" comparator="EQUALS" value="1.0" />
    <if_variable name="Sector" comparator="EQUALS" value="5.0" />
    <if_variable name="Sierra System" comparator="EQUALS" value="2.0" />
    <warning_popup_message message="Sector Transition" consoles="MHWESCO">Sector Transition in progress</warning_popup_message>
    <destroy_near type="all" radius="100000" centerX="50000" centerY="0" centerZ="50000" />
    <set_timer name="Transition" seconds="0.5" />
    <set_variable name="Grid 1 Transition" value="0.0" />
    <set_variable name="Sierra System" value="3.0" integer="yes" />
    <set_variable name="Sector" value="4.0" integer="yes" />
  </event>
  <event name="Transition to Sector II" id_arme="3a83ddc5-d463-4358-98ae-98794a06b2a1" parent_id_arme="30aea8c2-2865-45a9-9fb9-6733e45b8246">
    <if_variable name="Sector" comparator="EQUALS" value="5.0" />
    <if_variable name="Sierra System" comparator="EQUALS" value="2.0" />
    <if_variable name="Grid A Transition" comparator="EQUALS" value="1.0" />
    <warning_popup_message message="Sector Transition" consoles="MHWESCO">Sector Transition in progress</warning_popup_message>
    <destroy_near type="all" radius="100000" centerX="50000" centerY="0" centerZ="50000" />
    <set_timer name="Transition" seconds="0.5" />
    <set_variable name="Grid A Transition" value="0.0" />
    <set_variable name="Sierra System" value="3.0" integer="yes" />
    <set_variable name="Sector" value="2.0" integer="yes" />
  </event>
  <event name="Transition to Sector VIII" id_arme="028372dd-4504-4a57-8db2-61b74a3f4ef7" parent_id_arme="30aea8c2-2865-45a9-9fb9-6733e45b8246">
    <if_variable name="Grid E Transition" comparator="EQUALS" value="1.0" />
    <if_variable name="Sector" comparator="EQUALS" value="5.0" />
    <if_variable name="Sierra System" comparator="EQUALS" value="2.0" />
    <warning_popup_message message="Sector Transition" consoles="MHWESCO">Sector Transition in progress</warning_popup_message>
    <destroy_near type="all" radius="100000" centerX="50000" centerY="0" centerZ="50000" />
    <set_timer name="Transition" seconds="0.5" />
    <set_variable name="Grid E Transition" value="0.0" />
    <set_variable name="Sierra System" value="3.0" integer="yes" />
    <set_variable name="Sector" value="8.0" integer="yes" />
  </event>
  <event name="Transition to (Bottom Right)" id_arme="9bf6dd2f-1aae-437d-89c3-505f85601f4f" parent_id_arme="30aea8c2-2865-45a9-9fb9-6733e45b8246">
    <if_variable name="Corner E5 Transition" comparator="EQUALS" value="1.0" />
    <if_variable name="Sector" comparator="EQUALS" value="5.0" />
    <if_variable name="Sierra System" comparator="EQUALS" value="2.0" />
    <warning_popup_message message="Sector Transition" consoles="MHWESCO">Sector Transition in progress</warning_popup_message>
    <destroy_near type="all" radius="100000" centerX="50000" centerY="0" centerZ="50000" />
    <set_timer name="Transition" seconds="0.5" />
    <set_variable name="Corner E5 Transition" value="0.0" />
    <set_variable name="Sierra System" value="3.0" integer="yes" />
    <set_variable name="Sector" value="9.0" integer="yes" />
  </event>
  <event name="Transition to (Top Right)" id_arme="615fe283-2eba-4608-a7e2-8175c5184a12" parent_id_arme="30aea8c2-2865-45a9-9fb9-6733e45b8246">
    <if_variable name="Corner A5 Transition" comparator="EQUALS" value="1.0" />
    <if_variable name="Sector" comparator="EQUALS" value="5.0" />
    <if_variable name="Sierra System" comparator="EQUALS" value="2.0" />
    <warning_popup_message message="Sector Transition" consoles="MHWESCO">Sector Transition in progress</warning_popup_message>
    <destroy_near type="all" radius="100000" centerX="50000" centerY="0" centerZ="50000" />
    <set_timer name="Transition" seconds="0.5" />
    <set_variable name="Corner A5 Transition" value="0.0" />
    <set_variable name="Sierra System" value="3.0" integer="yes" />
    <set_variable name="Sector" value="3.0" integer="yes" />
  </event>
  <event name="Transition to (Bottom Left)" id_arme="5dc7564e-25ee-41d0-afa3-3a5909324a2c" parent_id_arme="30aea8c2-2865-45a9-9fb9-6733e45b8246">
    <if_variable name="Corner E1 Transition" comparator="EQUALS" value="1.0" />
    <if_variable name="Sector" comparator="EQUALS" value="5.0" />
    <if_variable name="Sierra System" comparator="EQUALS" value="2.0" />
    <warning_popup_message message="Sector Transition" consoles="MHWESCO">Sector Transition in progress</warning_popup_message>
    <destroy_near type="all" radius="100000" centerX="50000" centerY="0" centerZ="50000" />
    <set_timer name="Transition" seconds="0.5" />
    <set_variable name="Corner E1 Transition" value="0.0" />
    <set_variable name="Sierra System" value="3.0" integer="yes" />
    <set_variable name="Sector" value="7.0" integer="yes" />
  </event>
  <event name="Transition to (Top Left)" id_arme="f3a7a87e-8ff7-4b6e-a727-c7346fb5e4d6" parent_id_arme="30aea8c2-2865-45a9-9fb9-6733e45b8246">
    <if_variable name="Corner A1 Transition" comparator="EQUALS" value="1.0" />
    <if_variable name="Sector" comparator="EQUALS" value="5.0" />
    <if_variable name="Sierra System" comparator="EQUALS" value="2.0" />
    <warning_popup_message message="Sector Transition" consoles="MHWESCO">Sector Transition in progress</warning_popup_message>
    <destroy_near type="all" radius="100000" centerX="50000" centerY="0" centerZ="50000" />
    <set_timer name="Transition" seconds="0.5" />
    <set_variable name="Corner A1 Transition" value="0.0" />
    <set_variable name="Sierra System" value="3.0" integer="yes" />
    <set_variable name="Sector" value="1.0" integer="yes" />
  </event>
  <folder_arme name="Sector Entities" id_arme="330c0df9-680a-4d42-a784-d265fe0bee39" parent_id_arme="5d993fd3-e769-4ed6-a339-601c87afe77a" />
  <event name="Generate Sector Entities" id_arme="f63eb59f-5c35-4cfe-a2c5-d5832e947e75" parent_id_arme="330c0df9-680a-4d42-a784-d265fe0bee39">
    <if_variable name="Sierra System" comparator="EQUALS" value="2.0" />
    <if_variable name="Sector" comparator="EQUALS" value="5.0" />
    <if_variable name="Sector Entities" comparator="EQUALS" value="1.0" />
    <set_variable name="ExitorRetreat" value="0.0" />
    <set_variable name="Sector Entities" value="2.0" />
    <set_variable name="MissionCode" value="1.0" />
  </event>
  <event name="Settings" id_arme="4ccc0c21-f980-4050-b088-11c633e3706d" parent_id_arme="330c0df9-680a-4d42-a784-d265fe0bee39">
    <if_variable name="Sector" comparator="EQUALS" value="5.0" />
    <if_variable name="Sierra System" comparator="EQUALS" value="2.0" />
    <if_variable name="Sector Entities" comparator="EQUALS" value="2.0" />
    <set_variable name="Sector Entities" value="3.0" />
  </event>
  <event name="Destroy Sector Entities" id_arme="3806d85e-dc4b-4fce-881b-b96d4498ce54" parent_id_arme="330c0df9-680a-4d42-a784-d265fe0bee39">
    <if_variable name="Sierra System" comparator="EQUALS" value="3.0" />
    <set_variable name="Sierra System" value="System" integer="yes" />
    <set_variable name="Sector Entities" value="0.0" />
  </event>
  <folder_arme name="Sierra Sector VI" id_arme="ed9d4547-dc76-4969-b431-8ce98ea484a4" parent_id_arme="e9246d5c-950d-4fec-a3ee-d076de7edef0" />
  <event name="Create Sierra Sector VI" id_arme="0e059e13-bed8-4cf1-8622-a8e55effcbb8" parent_id_arme="ed9d4547-dc76-4969-b431-8ce98ea484a4">
    <if_variable name="Sierra System" comparator="EQUALS" value="1.0" />
    <if_variable name="Sector" comparator="EQUALS" value="6.0" />
    <if_timer_finished name="Transition" />
    <set_skybox_index index="26" />
    <set_variable name="Sector Entities" value="1.0" />
    <set_variable name="Sierra System" value="2.0" />
    <set_variable name="Grid A Transition Enabled" value="1.0" />
    <set_variable name="Grid E Transition Enabled" value="1.0" />
    <set_variable name="Grid 1 Transition Enabled" value="1.0" />
    <set_variable name="Grid 5 Transition Enabled" value="0.0" />
    <set_variable name="Corner A1 Transition Enabled" value="1.0" />
    <set_variable name="Corner A5 Transition Enabled" value="0.0" />
    <set_variable name="Corner E1 Transition Enabled" value="1.0" />
    <set_variable name="Corner E5 Transition Enabled" value="0.0" />
    <create count="50" type="nebulas" startX="87276.0" startY="0.0" startZ="57475.0" endX="46811.0" endY="0.0" endZ="74219.0" randomRange="3700" />
    <create count="15" type="mines" startX="47907.0" startY="0.0" startZ="50498.0" radius="20174" randomRange="26322" randomSeed="1" />
    <create count="150" type="asteroids" startX="60964.0" startY="0.0" startZ="29169.0" endX="10133.0" endY="0.0" endZ="51495.0" randomRange="12703" />
    <create count="150" type="asteroids" startX="84884.0" startY="0.0" startZ="15116.0" endX="70731.0" endY="0.0" endZ="32657.0" randomRange="15000" />
  </event>
  <folder_arme name="Navigation" id_arme="715f7151-966c-478c-ba66-7844a8d8bbf1" parent_id_arme="ed9d4547-dc76-4969-b431-8ce98ea484a4" />
  <event name="Transition to Sector V" id_arme="e692c3db-85b1-41a4-a2ee-7a70375a6ffb" parent_id_arme="715f7151-966c-478c-ba66-7844a8d8bbf1">
    <if_variable name="Grid 1 Transition" comparator="EQUALS" value="1.0" />
    <if_variable name="Sector" comparator="EQUALS" value="6.0" />
    <if_variable name="Sierra System" comparator="EQUALS" value="2.0" />
    <warning_popup_message message="Sector Transition" consoles="MHWESCO">Sector Transition in progress</warning_popup_message>
    <destroy_near type="all" radius="100000" centerX="50000" centerY="0" centerZ="50000" />
    <set_timer name="Transition" seconds="0.5" />
    <set_variable name="Grid 1 Transition" value="0.0" />
    <set_variable name="Sierra System" value="3.0" integer="yes" />
    <set_variable name="Sector" value="5.0" integer="yes" />
  </event>
  <event name="Transition to Sector III" id_arme="1edef728-130d-476c-8be4-61e6b9719570" parent_id_arme="715f7151-966c-478c-ba66-7844a8d8bbf1">
    <if_variable name="Grid A Transition" comparator="EQUALS" value="1.0" />
    <if_variable name="Sector" comparator="EQUALS" value="6.0" />
    <if_variable name="Sierra System" comparator="EQUALS" value="2.0" />
    <warning_popup_message message="Sector Transition" consoles="MHWESCO">Sector Transition in progress</warning_popup_message>
    <destroy_near type="all" radius="100000" centerX="50000" centerY="0" centerZ="50000" />
    <set_timer name="Transition" seconds="0.5" />
    <set_variable name="Grid A Transition" value="0.0" />
    <set_variable name="Sierra System" value="3.0" integer="yes" />
    <set_variable name="Sector" value="3.0" integer="yes" />
  </event>
  <event name="Transition to Sector IX" id_arme="8f2ed386-d7b0-4635-8dc6-0bf5f1a55812" parent_id_arme="715f7151-966c-478c-ba66-7844a8d8bbf1">
    <if_variable name="Grid E Transition" comparator="EQUALS" value="1.0" />
    <if_variable name="Sector" comparator="EQUALS" value="6.0" />
    <if_variable name="Sierra System" comparator="EQUALS" value="2.0" />
    <warning_popup_message message="Sector Transition" consoles="MHWESCO">Sector Transition in progress</warning_popup_message>
    <destroy_near type="all" radius="100000" centerX="50000" centerY="0" centerZ="50000" />
    <set_timer name="Transition" seconds="0.5" />
    <set_variable name="Grid E Transition" value="0.0" />
    <set_variable name="Sierra System" value="3.0" integer="yes" />
    <set_variable name="Sector" value="9.0" integer="yes" />
  </event>
  <event name="Transition to (Bottom Left)" id_arme="22ee876d-65d0-4f44-8a9c-37e355395bd9" parent_id_arme="715f7151-966c-478c-ba66-7844a8d8bbf1">
    <if_variable name="Corner E1 Transition" comparator="EQUALS" value="1.0" />
    <if_variable name="Sector" comparator="EQUALS" value="6.0" />
    <if_variable name="Sierra System" comparator="EQUALS" value="2.0" />
    <warning_popup_message message="Sector Transition" consoles="MHWESCO">Sector Transition in progress</warning_popup_message>
    <destroy_near type="all" radius="100000" centerX="50000" centerY="0" centerZ="50000" />
    <set_timer name="Transition" seconds="0.5" />
    <set_variable name="Corner E1 Transition" value="0.0" />
    <set_variable name="Sierra System" value="3.0" integer="yes" />
    <set_variable name="Sector" value="8.0" integer="yes" />
  </event>
  <event name="Transition to (Top Left)" id_arme="05f70fd6-6742-4519-bfc0-7b5e1a6d5919" parent_id_arme="715f7151-966c-478c-ba66-7844a8d8bbf1">
    <if_variable name="Corner A1 Transition" comparator="EQUALS" value="1.0" />
    <if_variable name="Sector" comparator="EQUALS" value="6.0" />
    <if_variable name="Sierra System" comparator="EQUALS" value="2.0" />
    <warning_popup_message message="Sector Transition" consoles="MHWESCO">Sector Transition in progress</warning_popup_message>
    <destroy_near type="all" radius="100000" centerX="50000" centerY="0" centerZ="50000" />
    <set_timer name="Transition" seconds="0.5" />
    <set_variable name="Corner A1 Transition" value="0.0" />
    <set_variable name="Sierra System" value="3.0" integer="yes" />
    <set_variable name="Sector" value="2.0" integer="yes" />
  </event>
  <folder_arme name="Sector Entities" id_arme="d90760ba-3f0f-449e-ab34-5e17a653a654" parent_id_arme="ed9d4547-dc76-4969-b431-8ce98ea484a4" />
  <event name="Generate Sector Entities" id_arme="65eb1d9a-ef67-417b-b651-18d892923346" parent_id_arme="d90760ba-3f0f-449e-ab34-5e17a653a654">
    <if_variable name="Sierra System" comparator="EQUALS" value="2.0" />
    <if_variable name="Sector" comparator="EQUALS" value="6.0" />
    <if_variable name="Sector Entities" comparator="EQUALS" value="1.0" />
    <set_variable name="ExitorRetreat" value="0.0" />
    <set_variable name="Sector Entities" value="2.0" />
    <set_variable name="MissionCode" value="1.0" />
  </event>
  <event name="Settings" id_arme="9641fd3f-3a05-407a-92a7-3ca24ff26591" parent_id_arme="d90760ba-3f0f-449e-ab34-5e17a653a654">
    <if_variable name="Sector" comparator="EQUALS" value="6.0" />
    <if_variable name="Sierra System" comparator="EQUALS" value="2.0" />
    <if_variable name="Sector Entities" comparator="EQUALS" value="2.0" />
    <set_variable name="Sector Entities" value="3.0" />
  </event>
  <event name="Destroy Sector Entities" id_arme="b486e8a8-84d5-4299-a22c-77cc07866a13" parent_id_arme="d90760ba-3f0f-449e-ab34-5e17a653a654">
    <if_variable name="Sierra System" comparator="EQUALS" value="3.0" />
    <set_variable name="Sierra System" value="System" integer="yes" />
    <set_variable name="Sector Entities" value="0.0" />
  </event>
  <folder_arme name="Sierra Sector VII" id_arme="a7bbc702-4bae-47a0-b39c-bc0ef1992174" parent_id_arme="e9246d5c-950d-4fec-a3ee-d076de7edef0" />
  <event name="Create Sierra Sector VII" id_arme="3bf9088b-36be-448d-aeeb-df2675535ade" parent_id_arme="a7bbc702-4bae-47a0-b39c-bc0ef1992174">
    <if_variable name="Sierra System" comparator="EQUALS" value="1.0" />
    <if_variable name="Sector" comparator="EQUALS" value="7.0" />
    <if_timer_finished name="Transition" />
    <set_skybox_index index="26" />
    <set_variable name="Sector Entities" value="1.0" />
    <set_variable name="Sierra System" value="2.0" />
    <set_variable name="Grid 5 Transition Enabled" value="1.0" />
    <set_variable name="Grid 1 Transition Enabled" value="0.0" />
    <set_variable name="Grid E Transition Enabled" value="0.0" />
    <set_variable name="Grid A Transition Enabled" value="1.0" />
    <set_variable name="Corner A1 Transition Enabled" value="0.0" />
    <set_variable name="Corner A5 Transition Enabled" value="1.0" />
    <set_variable name="Corner E1 Transition Enabled" value="0.0" />
    <set_variable name="Corner E5 Transition Enabled" value="0.0" />
    <create count="250" type="nebulas" startX="79004.0" startY="0.0" startZ="54086.0" endX="22592.0" endY="0.0" endZ="76312.0" randomRange="11285" />
    <create count="100" type="nebulas" startX="66545.0" startY="0.0" startZ="14717.0" endX="17708.0" endY="0.0" endZ="33953.0" randomRange="10000" />
  </event>
  <folder_arme name="Navigation" id_arme="71f5e22b-ba31-4efc-9d79-ccac229cd717" parent_id_arme="a7bbc702-4bae-47a0-b39c-bc0ef1992174" />
  <event name="Transition to Sector VIII" id_arme="8a2fc5a4-79c7-4562-b4fe-c2b842706c5a" parent_id_arme="71f5e22b-ba31-4efc-9d79-ccac229cd717">
    <if_variable name="Grid 5 Transition" comparator="EQUALS" value="1.0" />
    <if_variable name="Sector" comparator="EQUALS" value="7.0" />
    <if_variable name="Sierra System" comparator="EQUALS" value="2.0" />
    <warning_popup_message message="Sector Transition" consoles="MHWESCO">Sector Transition in progress</warning_popup_message>
    <destroy_near type="all" radius="100000" centerX="50000" centerY="0" centerZ="50000" />
    <set_timer name="Transition" seconds="0.5" />
    <set_variable name="Grid 5 Transition" value="0.0" />
    <set_variable name="Sierra System" value="3.0" integer="yes" />
    <set_variable name="Sector" value="8.0" integer="yes" />
  </event>
  <event name="Transition to Sector IV" id_arme="cf15d28e-0337-47e0-9733-c81e1235f939" parent_id_arme="71f5e22b-ba31-4efc-9d79-ccac229cd717">
    <if_variable name="Grid A Transition" comparator="EQUALS" value="1.0" />
    <if_variable name="Sector" comparator="EQUALS" value="7.0" />
    <if_variable name="Sierra System" comparator="EQUALS" value="2.0" />
    <warning_popup_message message="Sector Transition" consoles="MHWESCO">Sector Transition in progress</warning_popup_message>
    <destroy_near type="all" radius="100000" centerX="50000" centerY="0" centerZ="50000" />
    <set_timer name="Transition" seconds="0.5" />
    <set_variable name="Grid A Transition" value="0.0" />
    <set_variable name="Sierra System" value="3.0" integer="yes" />
    <set_variable name="Sector" value="4.0" integer="yes" />
  </event>
  <event name="Transition to (Top Right)" id_arme="fa2ac5c8-24f8-48a9-be02-9cfc53e336cb" parent_id_arme="71f5e22b-ba31-4efc-9d79-ccac229cd717">
    <if_variable name="Corner A5 Transition" comparator="EQUALS" value="1.0" />
    <if_variable name="Sector" comparator="EQUALS" value="7.0" />
    <if_variable name="Sierra System" comparator="EQUALS" value="2.0" />
    <warning_popup_message message="Sector Transition" consoles="MHWESCO">Sector Transition in progress</warning_popup_message>
    <destroy_near type="all" radius="100000" centerX="50000" centerY="0" centerZ="50000" />
    <set_timer name="Transition" seconds="0.5" />
    <set_variable name="Corner A5 Transition" value="0.0" />
    <set_variable name="Sierra System" value="3.0" integer="yes" />
    <set_variable name="Sector" value="5.0" integer="yes" />
  </event>
  <folder_arme name="Sector Entities" id_arme="42787b99-bb60-48c2-8327-05c7f8f8bf59" parent_id_arme="a7bbc702-4bae-47a0-b39c-bc0ef1992174" />
  <event name="Generate Sector Entities" id_arme="6852d8cb-888f-4f2e-809a-7df1e8721a89" parent_id_arme="42787b99-bb60-48c2-8327-05c7f8f8bf59">
    <if_variable name="Sierra System" comparator="EQUALS" value="2.0" />
    <if_variable name="Sector" comparator="EQUALS" value="7.0" />
    <if_variable name="Sector Entities" comparator="EQUALS" value="1.0" />
    <set_variable name="ExitorRetreat" value="0.0" />
    <set_variable name="Sector Entities" value="2.0" />
    <set_variable name="MissionCode" value="1.0" />
  </event>
  <event name="Settings" id_arme="65ecfa77-2912-4fa7-9a52-eb728ef4795a" parent_id_arme="42787b99-bb60-48c2-8327-05c7f8f8bf59">
    <if_variable name="Sector" comparator="EQUALS" value="7.0" />
    <if_variable name="Sierra System" comparator="EQUALS" value="2.0" />
    <if_variable name="Sector Entities" comparator="EQUALS" value="2.0" />
    <set_variable name="Sector Entities" value="3.0" />
  </event>
  <event name="Destroy Sector Entities" id_arme="2502b43f-8e81-4f9b-bd7c-fded3280d5a1" parent_id_arme="42787b99-bb60-48c2-8327-05c7f8f8bf59">
    <if_variable name="Sierra System" comparator="EQUALS" value="3.0" />
    <set_variable name="Sierra System" value="System" integer="yes" />
    <set_variable name="Sector Entities" value="0.0" />
  </event>
  <folder_arme name="Sierra Sector VIII" id_arme="579e0cc2-c3a1-4669-bd73-58d40c59671a" parent_id_arme="e9246d5c-950d-4fec-a3ee-d076de7edef0" />
  <event name="Create Sierra Sector VIII" id_arme="447352d5-a341-43c6-829e-5a408cad4dce" parent_id_arme="579e0cc2-c3a1-4669-bd73-58d40c59671a">
    <if_variable name="Sierra System" comparator="EQUALS" value="1.0" />
    <if_variable name="Sector" comparator="EQUALS" value="8.0" />
    <if_timer_finished name="Transition" />
    <set_skybox_index index="26" />
    <set_variable name="Sector Entities" value="1.0" />
    <set_variable name="Sierra System" value="2.0" />
    <set_variable name="Grid 5 Transition Enabled" value="1.0" />
    <set_variable name="Grid 1 Transition Enabled" value="1.0" />
    <set_variable name="Grid E Transition Enabled" value="0.0" />
    <set_variable name="Grid A Transition Enabled" value="1.0" />
    <set_variable name="Corner A1 Transition Enabled" value="1.0" />
    <set_variable name="Corner A5 Transition Enabled" value="1.0" />
    <set_variable name="Corner E1 Transition Enabled" value="0.0" />
    <set_variable name="Corner E5 Transition Enabled" value="0.0" />
    <create count="213" type="nebulas" startX="28828.0" startY="0.0" startZ="39884.0" endX="22592.0" endY="0.0" endZ="76312.0" randomRange="11285" />
    <create count="63" type="nebulas" startX="80220.0" startY="0.0" startZ="62628.0" endX="58733.0" endY="0.0" endZ="24429.0" randomRange="10000" />
    <create count="47" type="asteroids" startX="32472.0" startY="0.0" startZ="31465.0" endX="16137.0" endY="0.0" endZ="19780.0" randomRange="10000" />
    <create count="3" type="mines" startX="58231.0" startY="0.0" startZ="48052.0" endX="58231.0" endY="0.0" endZ="48052.0" randomRange="33039" />
  </event>
  <folder_arme name="Navigation" id_arme="692d5efe-abdc-49fe-b74d-fbcaaeb0f0b9" parent_id_arme="579e0cc2-c3a1-4669-bd73-58d40c59671a" />
  <event name="Transition to Sector IX" id_arme="a87278c0-628d-4e3b-a782-f08ae0ba1fd2" parent_id_arme="692d5efe-abdc-49fe-b74d-fbcaaeb0f0b9">
    <if_variable name="Grid 5 Transition" comparator="EQUALS" value="1.0" />
    <if_variable name="Sector" comparator="EQUALS" value="8.0" />
    <if_variable name="Sierra System" comparator="EQUALS" value="2.0" />
    <warning_popup_message message="Sector Transition" consoles="MHWESCO">Sector Transition in progress</warning_popup_message>
    <destroy_near type="all" radius="100000" centerX="50000" centerY="0" centerZ="50000" />
    <set_timer name="Transition" seconds="0.5" />
    <set_variable name="Grid 5 Transition" value="0.0" />
    <set_variable name="Sierra System" value="3.0" integer="yes" />
    <set_variable name="Sector" value="9.0" integer="yes" />
  </event>
  <event name="Transition to Sector VII" id_arme="a1f6b7be-0d56-41ec-a601-39a2cfbd9c64" parent_id_arme="692d5efe-abdc-49fe-b74d-fbcaaeb0f0b9">
    <if_variable name="Grid 1 Transition" comparator="EQUALS" value="1.0" />
    <if_variable name="Sector" comparator="EQUALS" value="8.0" />
    <if_variable name="Sierra System" comparator="EQUALS" value="2.0" />
    <warning_popup_message message="Sector Transition" consoles="MHWESCO">Sector Transition in progress</warning_popup_message>
    <destroy_near type="all" radius="100000" centerX="50000" centerY="0" centerZ="50000" />
    <set_timer name="Transition" seconds="0.5" />
    <set_variable name="Grid 1 Transition" value="0.0" />
    <set_variable name="Sierra System" value="3.0" integer="yes" />
    <set_variable name="Sector" value="7.0" integer="yes" />
  </event>
  <event name="Transition to Sector V" id_arme="019654e2-d5a0-4835-b093-2bc9a8148fd3" parent_id_arme="692d5efe-abdc-49fe-b74d-fbcaaeb0f0b9">
    <if_variable name="Grid A Transition" comparator="EQUALS" value="1.0" />
    <if_variable name="Sector" comparator="EQUALS" value="8.0" />
    <if_variable name="Sierra System" comparator="EQUALS" value="2.0" />
    <warning_popup_message message="Sector Transition" consoles="MHWESCO">Sector Transition in progress</warning_popup_message>
    <destroy_near type="all" radius="100000" centerX="50000" centerY="0" centerZ="50000" />
    <set_timer name="Transition" seconds="0.5" />
    <set_variable name="Grid A Transition" value="0.0" />
    <set_variable name="Sierra System" value="3.0" integer="yes" />
    <set_variable name="Sector" value="5.0" integer="yes" />
  </event>
  <event name="Transition to (Top Right)" id_arme="74f1685c-3801-4e02-8a5d-652cf2384687" parent_id_arme="692d5efe-abdc-49fe-b74d-fbcaaeb0f0b9">
    <if_variable name="Corner A5 Transition" comparator="EQUALS" value="1.0" />
    <if_variable name="Sector" comparator="EQUALS" value="8.0" />
    <if_variable name="Sierra System" comparator="EQUALS" value="2.0" />
    <warning_popup_message message="Sector Transition" consoles="MHWESCO">Sector Transition in progress</warning_popup_message>
    <destroy_near type="all" radius="100000" centerX="50000" centerY="0" centerZ="50000" />
    <set_timer name="Transition" seconds="0.5" />
    <set_variable name="Corner A5 Transition" value="0.0" />
    <set_variable name="Sierra System" value="3.0" integer="yes" />
    <set_variable name="Sector" value="6.0" integer="yes" />
  </event>
  <event name="Transition to (Top Left)" id_arme="f318a0fb-5d26-48d3-b1a4-d67f7bbb1dd8" parent_id_arme="692d5efe-abdc-49fe-b74d-fbcaaeb0f0b9">
    <if_variable name="Corner A1 Transition" comparator="EQUALS" value="1.0" />
    <if_variable name="Sector" comparator="EQUALS" value="8.0" />
    <if_variable name="Sierra System" comparator="EQUALS" value="2.0" />
    <warning_popup_message message="Sector Transition" consoles="MHWESCO">Sector Transition in progress</warning_popup_message>
    <destroy_near type="all" radius="100000" centerX="50000" centerY="0" centerZ="50000" />
    <set_timer name="Transition" seconds="0.5" />
    <set_variable name="Corner A1 Transition" value="0.0" />
    <set_variable name="Sierra System" value="3.0" integer="yes" />
    <set_variable name="Sector" value="4.0" integer="yes" />
  </event>
  <folder_arme name="System - Jump Gate Settings" id_arme="4d6c88be-0260-4754-ad88-f0717bbc1da0" parent_id_arme="692d5efe-abdc-49fe-b74d-fbcaaeb0f0b9" />
  <event name="Gate Offline" id_arme="a9ff9b26-30d2-4758-b324-da88afc3634d" parent_id_arme="4d6c88be-0260-4754-ad88-f0717bbc1da0">
    <if_variable name="Sector" comparator="EQUALS" value="8" />
    <if_variable name="Sierra System" comparator="EQUALS" value="2.0" />
    <if_variable name="Gate System" comparator="EQUALS" value="0.0" />
    <set_object_property property="rollDelta" value="0.3" name="Volantis Gate" />
  </event>
  <folder_arme name="Tracking System" id_arme="6ceb59da-0abc-45c0-ad4f-f07d81aa4787" parent_id_arme="4d6c88be-0260-4754-ad88-f0717bbc1da0" />
  <event name="Ship1 Activation Range" id_arme="0bcd8ea7-e4b5-478c-af42-31349d8830e0" parent_id_arme="6ceb59da-0abc-45c0-ad4f-f07d81aa4787">
    <if_variable name="Sector" comparator="EQUALS" value="8" />
    <if_variable name="Sierra System" comparator="EQUALS" value="2.0" />
    <if_variable name="Gate Tracking Ship1" comparator="EQUALS" value="0.0" />
    <if_distance player_slot1="0" name2="Volantis Gate" comparator="LESS" value="4000.0" />
    <if_variable name="Volantis Gate" comparator="EQUALS" value="1.0" />
    <set_variable name="shipsInrange" value="shipsInrange+1" />
    <set_variable name="Gate Tracking Ship1" value="1.0" />
  </event>
  <event name="Ship1 Out of Range" id_arme="ed2e874e-72ed-4c6b-82ae-1814ee7e9ef0" parent_id_arme="6ceb59da-0abc-45c0-ad4f-f07d81aa4787">
    <if_variable name="Sector" comparator="EQUALS" value="8" />
    <if_variable name="Sierra System" comparator="EQUALS" value="2.0" />
    <if_variable name="Gate Tracking Ship1" comparator="EQUALS" value="1.0" />
    <if_distance player_slot1="0" name2="Volantis Gate" comparator="GREATER" value="4000.0" />
    <if_variable name="Volantis Gate" comparator="EQUALS" value="1.0" />
    <set_variable name="shipsInrange" value="shipsInrange-1" />
    <set_variable name="Gate Tracking Ship1" value="0.0" />
  </event>
  <event name="Ship2 Activation Range" id_arme="edfe88c2-ecd8-49d3-b57e-f8a689a093e4" parent_id_arme="6ceb59da-0abc-45c0-ad4f-f07d81aa4787">
    <if_variable name="Sector" comparator="EQUALS" value="8" />
    <if_variable name="Sierra System" comparator="EQUALS" value="2.0" />
    <if_variable name="Gate Tracking Ship2" comparator="EQUALS" value="0.0" />
    <if_distance player_slot1="1" name2="Volantis Gate" comparator="LESS" value="4000.0" />
    <if_variable name="Volantis Gate" comparator="EQUALS" value="1.0" />
    <set_variable name="shipsInrange" value="shipsInrange+1" />
    <set_variable name="Gate Tracking Ship2" value="1.0" />
  </event>
  <event name="Ship2 Out of Range" id_arme="c827ba52-3072-4107-856f-784e889715d3" parent_id_arme="6ceb59da-0abc-45c0-ad4f-f07d81aa4787">
    <if_variable name="Sector" comparator="EQUALS" value="8" />
    <if_variable name="Sierra System" comparator="EQUALS" value="2.0" />
    <if_variable name="Gate Tracking Ship2" comparator="EQUALS" value="1.0" />
    <if_distance player_slot1="1" name2="Volantis Gate" comparator="GREATER" value="4000.0" />
    <if_variable name="Volantis Gate" comparator="EQUALS" value="1.0" />
    <set_variable name="shipsInrange" value="shipsInrange-1" />
    <set_variable name="Gate Tracking Ship2" value="0.0" />
  </event>
  <event name="Ship3 Activation Range" id_arme="a84619fb-fc1e-4396-932c-5648234bd945" parent_id_arme="6ceb59da-0abc-45c0-ad4f-f07d81aa4787">
    <if_variable name="Sector" comparator="EQUALS" value="8" />
    <if_variable name="Sierra System" comparator="EQUALS" value="2.0" />
    <if_variable name="Gate Tracking Ship3" comparator="EQUALS" value="0.0" />
    <if_distance player_slot1="2" name2="Volantis Gate" comparator="LESS" value="4000.0" />
    <if_variable name="Volantis Gate" comparator="EQUALS" value="1.0" />
    <set_variable name="shipsInrange" value="shipsInrange+1" />
    <set_variable name="Gate Tracking Ship3" value="1.0" />
  </event>
  <event name="Ship3 Out of Range" id_arme="1da83874-7d95-4c8d-9355-c37e8ad7490b" parent_id_arme="6ceb59da-0abc-45c0-ad4f-f07d81aa4787">
    <if_variable name="Sector" comparator="EQUALS" value="8" />
    <if_variable name="Sierra System" comparator="EQUALS" value="2.0" />
    <if_variable name="Gate Tracking Ship3" comparator="EQUALS" value="1.0" />
    <if_distance player_slot1="2" name2="Volantis Gate" comparator="GREATER" value="4000.0" />
    <if_variable name="Volantis Gate" comparator="EQUALS" value="1.0" />
    <set_variable name="shipsInrange" value="shipsInrange-1" />
    <set_variable name="Gate Tracking Ship3" value="0.0" />
  </event>
  <event name="Ship4 Activation Range" id_arme="1f80066f-3a51-48da-b7ba-2107bd43cf02" parent_id_arme="6ceb59da-0abc-45c0-ad4f-f07d81aa4787">
    <if_variable name="Sector" comparator="EQUALS" value="8" />
    <if_variable name="Sierra System" comparator="EQUALS" value="2.0" />
    <if_variable name="Gate Tracking Ship4" comparator="EQUALS" value="0.0" />
    <if_distance player_slot1="3" name2="Volantis Gate" comparator="LESS" value="4000.0" />
    <if_variable name="Volantis Gate" comparator="EQUALS" value="1.0" />
    <set_variable name="shipsInrange" value="shipsInrange+1" />
    <set_variable name="Gate Tracking Ship4" value="1.0" />
  </event>
  <event name="Ship4 Out of Range" id_arme="37d7ae5e-60cb-4674-be37-3b9b503c6e64" parent_id_arme="6ceb59da-0abc-45c0-ad4f-f07d81aa4787">
    <if_variable name="Sector" comparator="EQUALS" value="8" />
    <if_variable name="Sierra System" comparator="EQUALS" value="2.0" />
    <if_variable name="Gate Tracking Ship4" comparator="EQUALS" value="1.0" />
    <if_distance player_slot1="3" name2="Volantis Gate" comparator="GREATER" value="4000.0" />
    <if_variable name="Volantis Gate" comparator="EQUALS" value="1.0" />
    <set_variable name="shipsInrange" value="shipsInrange-1" />
    <set_variable name="Gate Tracking Ship4" value="0.0" />
  </event>
  <event name="Ship5 Activation Range" id_arme="95707f40-cd9d-44c2-91b5-950055fb4827" parent_id_arme="6ceb59da-0abc-45c0-ad4f-f07d81aa4787">
    <if_variable name="Sector" comparator="EQUALS" value="8" />
    <if_variable name="Sierra System" comparator="EQUALS" value="2.0" />
    <if_variable name="Gate Tracking Ship5" comparator="EQUALS" value="0.0" />
    <if_distance player_slot1="4" name2="Volantis Gate" comparator="LESS" value="4000.0" />
    <if_variable name="Volantis Gate" comparator="EQUALS" value="1.0" />
    <set_variable name="shipsInrange" value="shipsInrange+1" />
    <set_variable name="Gate Tracking Ship5" value="1.0" />
  </event>
  <event name="Ship5 Out of Range" id_arme="b077b3c6-bdaf-4670-8e00-41197773c7a4" parent_id_arme="6ceb59da-0abc-45c0-ad4f-f07d81aa4787">
    <if_variable name="Sector" comparator="EQUALS" value="8" />
    <if_variable name="Sierra System" comparator="EQUALS" value="2.0" />
    <if_variable name="Gate Tracking Ship5" comparator="EQUALS" value="1.0" />
    <if_distance player_slot1="4" name2="Volantis Gate" comparator="GREATER" value="4000.0" />
    <if_variable name="Volantis Gate" comparator="EQUALS" value="1.0" />
    <set_variable name="shipsInrange" value="shipsInrange-1" />
    <set_variable name="Gate Tracking Ship5" value="0.0" />
  </event>
  <event name="Ship6 Activation Range" id_arme="a0ffbffc-5e6e-47f4-8bfe-2c36db6240cb" parent_id_arme="6ceb59da-0abc-45c0-ad4f-f07d81aa4787">
    <if_variable name="Sector" comparator="EQUALS" value="8" />
    <if_variable name="Sierra System" comparator="EQUALS" value="2.0" />
    <if_variable name="Gate Tracking Ship6" comparator="EQUALS" value="0.0" />
    <if_distance player_slot1="5" name2="Volantis Gate" comparator="LESS" value="4000.0" />
    <if_variable name="Volantis Gate" comparator="EQUALS" value="1.0" />
    <set_variable name="shipsInrange" value="shipsInrange+1" />
    <set_variable name="Gate Tracking Ship6" value="1.0" />
  </event>
  <event name="Ship6 Out of Range" id_arme="d35d51dd-c9a3-4e12-b87a-43b1e2b80fd7" parent_id_arme="6ceb59da-0abc-45c0-ad4f-f07d81aa4787">
    <if_variable name="Sector" comparator="EQUALS" value="8" />
    <if_variable name="Sierra System" comparator="EQUALS" value="2.0" />
    <if_variable name="Gate Tracking Ship6" comparator="EQUALS" value="1.0" />
    <if_distance player_slot1="5" name2="Volantis Gate" comparator="GREATER" value="4000.0" />
    <if_variable name="Volantis Gate" comparator="EQUALS" value="1.0" />
    <set_variable name="shipsInrange" value="shipsInrange-1" />
    <set_variable name="Gate Tracking Ship6" value="0.0" />
  </event>
  <event name="Ship7 Activation Range" id_arme="018e1127-0a32-4d58-a14d-6ed180e1785b" parent_id_arme="6ceb59da-0abc-45c0-ad4f-f07d81aa4787">
    <if_variable name="Sector" comparator="EQUALS" value="8" />
    <if_variable name="Sierra System" comparator="EQUALS" value="2.0" />
    <if_variable name="Gate Tracking Ship7" comparator="EQUALS" value="0.0" />
    <if_distance player_slot1="6" name2="Volantis Gate" comparator="LESS" value="4000.0" />
    <if_variable name="Volantis Gate" comparator="EQUALS" value="1.0" />
    <set_variable name="shipsInrange" value="shipsInrange+1" />
    <set_variable name="Gate Tracking Ship7" value="1.0" />
  </event>
  <event name="Ship7 Out of Range" id_arme="cc411271-c92f-4b6d-81b4-6b22fbfdc565" parent_id_arme="6ceb59da-0abc-45c0-ad4f-f07d81aa4787">
    <if_variable name="Sector" comparator="EQUALS" value="8" />
    <if_variable name="Sierra System" comparator="EQUALS" value="2.0" />
    <if_variable name="Gate Tracking Ship7" comparator="EQUALS" value="1.0" />
    <if_distance player_slot1="6" name2="Volantis Gate" comparator="GREATER" value="4000.0" />
    <if_variable name="Volantis Gate" comparator="EQUALS" value="1.0" />
    <set_variable name="shipsInrange" value="shipsInrange-1" />
    <set_variable name="Gate Tracking Ship7" value="0.0" />
  </event>
  <event name="Ship8 Activation Range" id_arme="4bf9af52-fdf4-42e5-a2d0-2c378afe759e" parent_id_arme="6ceb59da-0abc-45c0-ad4f-f07d81aa4787">
    <if_variable name="Sector" comparator="EQUALS" value="8" />
    <if_variable name="Sierra System" comparator="EQUALS" value="2.0" />
    <if_variable name="Gate Tracking Ship8" comparator="EQUALS" value="0.0" />
    <if_distance player_slot1="7" name2="Volantis Gate" comparator="LESS" value="4000.0" />
    <if_variable name="Volantis Gate" comparator="EQUALS" value="1.0" />
    <set_variable name="shipsInrange" value="shipsInrange+1" />
    <set_variable name="Gate Tracking Ship8" value="1.0" />
  </event>
  <event name="Ship8 Out of Range" id_arme="b6acd139-2747-4532-bfea-56691d36955e" parent_id_arme="6ceb59da-0abc-45c0-ad4f-f07d81aa4787">
    <if_variable name="Sector" comparator="EQUALS" value="8" />
    <if_variable name="Sierra System" comparator="EQUALS" value="2.0" />
    <if_variable name="Gate Tracking Ship8" comparator="EQUALS" value="1.0" />
    <if_distance player_slot1="7" name2="Volantis Gate" comparator="GREATER" value="4000.0" />
    <if_variable name="Volantis Gate" comparator="EQUALS" value="1.0" />
    <set_variable name="shipsInrange" value="shipsInrange-1" />
    <set_variable name="Gate Tracking Ship8" value="0.0" />
  </event>
  <event name="Gate Online" id_arme="4875d78c-24a8-4ab3-9f5a-dbde7ec2b52e" parent_id_arme="4d6c88be-0260-4754-ad88-f0717bbc1da0">
    <if_variable name="Sector" comparator="EQUALS" value="8" />
    <if_variable name="Sierra System" comparator="EQUALS" value="2.0" />
    <if_variable name="Gate System" comparator="EQUALS" value="1.0" />
    <if_comms_button text="Activate Gate" />
    <if_variable name="Volantis Gate" comparator="EQUALS" value="1.0" />
    <incoming_comms_text from="Gate System" sideValue="playerSide" type="STATUS">Activating Gate^Locking signal...</incoming_comms_text>
    <set_object_property property="rollDelta" value="1.0" name="Volantis Gate" />
    <set_timer name="Gate System" seconds="5" />
    <set_variable name="Gate System" value="2.0" />
    <clear_comms_button text="Activate Gate" sideValue="playerSide" />
  </event>
  <event name="Jump Initiated" id_arme="b6457b4c-2f30-49ba-9c63-afa31d75f40b" parent_id_arme="4d6c88be-0260-4754-ad88-f0717bbc1da0">
    <if_variable name="Sector" comparator="EQUALS" value="8" />
    <if_variable name="Sierra System" comparator="EQUALS" value="2.0" />
    <if_comms_button text="Jump" />
    <if_variable name="Gate System" comparator="EQUALS" value="3.0" />
    <if_variable name="Volantis Gate" comparator="EQUALS" value="1.0" />
    <clear_comms_button text="Jump" sideValue="playerSide" />
    <set_variable name="Sierra System" value="3.0" integer="yes" />
    <set_variable name="System" value="0.0" />
    <destroy_near type="all" radius="100000" centerX="50000" centerY="0" centerZ="50000" />
    <set_variable name="Sierra to Volantis" value="1.0" />
    <set_variable name="Volantis System" value="1.0" />
    <set_variable name="Sector" value="4" />
    <set_variable name="shipsInrange" value="0.0" integer="yes" />
    <set_timer name="Transition" seconds="2" />
    <set_variable name="Gate System" value="0.0" />
    <set_variable name="ExitorRetreat" value="1.0" />
  </event>
  <folder_arme name="Sector Entities" id_arme="928ffe89-71bd-4a59-b718-997e00ee1010" parent_id_arme="579e0cc2-c3a1-4669-bd73-58d40c59671a" />
  <event name="Generate Sector Entities" id_arme="5c07582e-f593-44f2-887f-57d6f3d21dcd" parent_id_arme="928ffe89-71bd-4a59-b718-997e00ee1010">
    <if_variable name="Sierra System" comparator="EQUALS" value="2.0" />
    <if_variable name="Sector" comparator="EQUALS" value="8.0" />
    <if_variable name="Sector Entities" comparator="EQUALS" value="1.0" />
    <create type="genericMesh" x="50943.0" y="0.0" z="55465.0" name="Volantis Gate" meshFileName="dat\TSN\USFP\TSNGate.dxs" textureFileName="dat\TSN\USFP\TSNGate.png" colorRed="1.0" colorGreen="0.5" colorBlue="0.0" />
    <set_variable name="ExitorRetreat" value="0.0" />
    <set_variable name="Sector Entities" value="2.0" />
    <set_variable name="MissionCode" value="1.0" />
  </event>
  <event name="Settings" id_arme="d857984f-b4a8-42cd-815a-9dca227c92a6" parent_id_arme="928ffe89-71bd-4a59-b718-997e00ee1010">
    <if_variable name="Sector" comparator="EQUALS" value="8.0" />
    <if_variable name="Sierra System" comparator="EQUALS" value="2.0" />
    <if_variable name="Sector Entities" comparator="EQUALS" value="2.0" />
    <set_object_property property="artScale" value="1.0" name="Volantis Gate" />
    <set_object_property property="pushRadius" value="0.0" name="Volantis Gate" />
    <set_object_property property="angle" value="4.71238898" name="Volantis Gate" />
    <set_object_property property="rollDelta" value="0.3" name="Volantis Gate" />
    <set_variable name="Sector Entities" value="3.0" />
  </event>
  <event name="Destroy Sector Entities" id_arme="32bcdc9e-2cfc-495a-9efe-e235e75bc485" parent_id_arme="928ffe89-71bd-4a59-b718-997e00ee1010">
    <if_variable name="Sierra System" comparator="EQUALS" value="3.0" />
    <destroy name="Volantis Gate" />
    <set_variable name="Sierra System" value="System" integer="yes" />
    <set_variable name="Sector Entities" value="0.0" />
  </event>
  <event name="Arrival From Volantis" id_arme="5d9b0f0e-0ed5-4f34-9a4d-001ba998cf0f" parent_id_arme="579e0cc2-c3a1-4669-bd73-58d40c59671a">
    <if_variable name="Sector" comparator="EQUALS" value="8" />
    <if_variable name="Sierra System" comparator="EQUALS" value="2.0" />
    <if_variable name="Volantis to Sierra" comparator="EQUALS" value="1.0" />
    <if_timer_finished name="Transition" />
    <set_relative_position player_slot2="0" distance="4200" angle="0.0" name1="Volantis Gate" />
    <set_relative_position player_slot2="1" distance="4200" angle="5.0" name1="Volantis Gate" />
    <set_relative_position player_slot2="2" distance="4200" angle="10.0" name1="Volantis Gate" />
    <set_relative_position player_slot2="3" distance="4200" angle="15.0" name1="Volantis Gate" />
    <set_relative_position player_slot2="4" distance="4200" angle="20.0" name1="Volantis Gate" />
    <set_relative_position player_slot2="5" distance="4200" angle="355.0" name1="Volantis Gate" />
    <set_relative_position player_slot2="6" distance="4200" angle="350.0" name1="Volantis Gate" />
    <set_relative_position player_slot2="7" distance="4200" angle="345.0" name1="Volantis Gate" />
    <set_object_property property="angle" value="3.141592654" player_slot="0" />
    <set_object_property property="angle" value="3.141592654" player_slot="1" />
    <set_object_property property="angle" value="3.141592654" player_slot="2" />
    <set_object_property property="angle" value="3.141592654" player_slot="3" />
    <set_object_property property="angle" value="3.141592654" player_slot="4" />
    <set_object_property property="angle" value="3.141592654" player_slot="5" />
    <set_object_property property="angle" value="3.141592654" player_slot="6" />
    <set_object_property property="angle" value="3.141592654" player_slot="7" />
    <set_variable name="Volantis to Sierra" value="0.0" />
  </event>
  <folder_arme name="Sierra Sector IX" id_arme="278a558a-7624-4ba6-89d9-41a47fdeb7e0" parent_id_arme="e9246d5c-950d-4fec-a3ee-d076de7edef0" />
  <event name="Create Sierra Sector IX" id_arme="4fbdc4e1-2b61-4adc-8a74-c462f20cc8ad" parent_id_arme="278a558a-7624-4ba6-89d9-41a47fdeb7e0">
    <if_variable name="Sierra System" comparator="EQUALS" value="1.0" />
    <if_variable name="Sector" comparator="EQUALS" value="9.0" />
    <if_timer_finished name="Transition" />
    <set_skybox_index index="26" />
    <set_variable name="Sector Entities" value="1.0" />
    <set_variable name="Sierra System" value="2.0" />
    <set_variable name="Grid 5 Transition Enabled" value="0.0" />
    <set_variable name="Grid 1 Transition Enabled" value="1.0" />
    <set_variable name="Grid E Transition Enabled" value="0.0" />
    <set_variable name="Grid A Transition Enabled" value="1.0" />
    <set_variable name="Corner A1 Transition Enabled" value="1.0" />
    <set_variable name="Corner A5 Transition Enabled" value="0.0" />
    <set_variable name="Corner E1 Transition Enabled" value="0.0" />
    <set_variable name="Corner E5 Transition Enabled" value="0.0" />
    <create count="10" type="nebulas" startX="18206.0" startY="0.0" startZ="22591.0" endX="26579.0" endY="0.0" endZ="47607.0" randomRange="13049" />
    <create count="10" type="asteroids" startX="42725.0" startY="0.0" startZ="26179.0" endX="62359.0" endY="0.0" endZ="30963.0" randomRange="10929" />
    <create count="10" type="nebulas" startX="77608.0" startY="0.0" startZ="25980.0" endX="77608.0" endY="0.0" endZ="25980.0" randomRange="9015" />
    <create count="25" type="asteroids" startX="62758.0" startY="0.0" startZ="55681.0" endX="56280.0" endY="0.0" endZ="49401.0" randomRange="6966" />
    <create count="75" type="nebulas" startAngle="266.6" endAngle="0" startX="61761.0" startY="0.0" startZ="76411.0" radius="17222" randomRange="11929" />
  </event>
  <folder_arme name="Navigation" id_arme="e8279afb-bda8-41d3-bc4c-958356b3e9d9" parent_id_arme="278a558a-7624-4ba6-89d9-41a47fdeb7e0" />
  <event name="Transition to Sector VIII" id_arme="dd11ec7e-0566-4d5b-8d2e-38618cee228e" parent_id_arme="e8279afb-bda8-41d3-bc4c-958356b3e9d9">
    <if_variable name="Grid 1 Transition" comparator="EQUALS" value="1.0" />
    <if_variable name="Sector" comparator="EQUALS" value="9.0" />
    <if_variable name="Sierra System" comparator="EQUALS" value="2.0" />
    <warning_popup_message message="Sector Transition" consoles="MHWESCO">Sector Transition in progress</warning_popup_message>
    <destroy_near type="all" radius="100000" centerX="50000" centerY="0" centerZ="50000" />
    <set_timer name="Transition" seconds="0.5" />
    <set_variable name="Grid 1 Transition" value="0.0" />
    <set_variable name="Sierra System" value="3.0" integer="yes" />
    <set_variable name="Sector" value="8.0" integer="yes" />
  </event>
  <event name="Transition to Sector VI" id_arme="30d5d350-527f-47b1-9398-1760c484a200" parent_id_arme="e8279afb-bda8-41d3-bc4c-958356b3e9d9">
    <if_variable name="Grid A Transition" comparator="EQUALS" value="1.0" />
    <if_variable name="Sector" comparator="EQUALS" value="9.0" />
    <if_variable name="Sierra System" comparator="EQUALS" value="2.0" />
    <warning_popup_message message="Sector Transition" consoles="MHWESCO">Sector Transition in progress</warning_popup_message>
    <destroy_near type="all" radius="100000" centerX="50000" centerY="0" centerZ="50000" />
    <set_timer name="Transition" seconds="0.5" />
    <set_variable name="Grid A Transition" value="0.0" />
    <set_variable name="Sierra System" value="3.0" integer="yes" />
    <set_variable name="Sector" value="6.0" integer="yes" />
  </event>
  <event name="Transition to (Top Left)" id_arme="8b8369f4-1fe3-4b9f-b9b8-6c11a369c90f" parent_id_arme="e8279afb-bda8-41d3-bc4c-958356b3e9d9">
    <if_variable name="Corner A1 Transition" comparator="EQUALS" value="1.0" />
    <if_variable name="Sector" comparator="EQUALS" value="9.0" />
    <if_variable name="Sierra System" comparator="EQUALS" value="2.0" />
    <warning_popup_message message="Sector Transition" consoles="MHWESCO">Sector Transition in progress</warning_popup_message>
    <destroy_near type="all" radius="100000" centerX="50000" centerY="0" centerZ="50000" />
    <set_timer name="Transition" seconds="0.5" />
    <set_variable name="Corner A1 Transition" value="0.0" />
    <set_variable name="Sierra System" value="3.0" integer="yes" />
    <set_variable name="Sector" value="5.0" integer="yes" />
  </event>
  <folder_arme name="Sector Entities" id_arme="21ebb22b-bb3a-410b-b03a-0338c70cd08d" parent_id_arme="278a558a-7624-4ba6-89d9-41a47fdeb7e0" />
  <event name="Generate Sector Entities" id_arme="97706252-9de2-4d98-aa12-76734b2e116e" parent_id_arme="21ebb22b-bb3a-410b-b03a-0338c70cd08d">
    <if_variable name="Sierra System" comparator="EQUALS" value="2.0" />
    <if_variable name="Sector" comparator="EQUALS" value="9.0" />
    <if_variable name="Sector Entities" comparator="EQUALS" value="1.0" />
    <set_variable name="ExitorRetreat" value="0.0" />
    <set_variable name="Sector Entities" value="2.0" />
    <set_variable name="MissionCode" value="1.0" />
  </event>
  <event name="Settings" id_arme="13e7a353-609c-439d-998b-477dac64bc2a" parent_id_arme="21ebb22b-bb3a-410b-b03a-0338c70cd08d">
    <if_variable name="Sector" comparator="EQUALS" value="9.0" />
    <if_variable name="Sierra System" comparator="EQUALS" value="2.0" />
    <if_variable name="Sector Entities" comparator="EQUALS" value="2.0" />
    <set_variable name="Sector Entities" value="3.0" />
  </event>
  <event name="Destroy Sector Entities" id_arme="f1988204-a34a-440f-8b77-0394ae5ae61c" parent_id_arme="21ebb22b-bb3a-410b-b03a-0338c70cd08d">
    <if_variable name="Sierra System" comparator="EQUALS" value="3.0" />
    <set_variable name="Sierra System" value="System" integer="yes" />
    <set_variable name="Sector Entities" value="0.0" />
  </event>
</mission_data>